Workbook

Sheet LMS_Loan_Tape
A1: loan_id | B1: disbursement_date | C1: principal_amount | D1: interest_rate | E1: tenure_months | F1: product_type | G1: lender_name | H1: status | I1: total_interest_accrued | J1: processing_fee_collected | K1: disb_month
A2: LN-10001 | B2: 45739 | C2: 1990685 | D2: 13.17 | E2: 36 | F2: Personal Loan | G2: DMI | H2: Active | I2: 305868 | J2: 33318 | K2: =MONTH(B2) -> 3
A3: LN-10002 | B3: 45811 | C3: 472946 | D3: 16.22 | E3: 24 | F3: Business Loan | G3: Tata Capital | H3: Active | I3: 70319 | J3: 9347 | K3: =MONTH(B3) -> 6
A4: LN-10003 | B4: 45891 | C4: 1164468 | D4: 13.4 | E4: 60 | F4: Home Loan | G4: Piramal | H4: Active | I4: 117029 | J4: 12951 | K4: =MONTH(B4) -> 8
A5: LN-10004 | B5: 46078 | C5: 1287900 | D5: 9.09 | E5: 24 | F5: Personal Loan | G5: Northern Arc | H5: Active | I5: 19511 | J5: 24107 | K5: =MONTH(B5) -> 2
A6: LN-10005 | B6: 45744 | C6: 274729 | D6: 12.7 | E6: 48 | F6: Personal Loan | G6: Piramal | H6: Active | I6: 37798 | J6: 2801 | K6: =MONTH(B6) -> 3
A7: LN-10006 | B7: 45736 | C7: 2292520 | D7: 8.94 | E7: 24 | F7: Business Loan | G7: DMI | H7: Closed | I7: 239109 | J7: 45022 | K7: =MONTH(B7) -> 3
A8: LN-10007 | B8: 45949 | C8: 370948 | D8: 13.8 | E8: 36 | F8: Gold Loan | G8: Piramal | H8: Active | I8: 29861 | J8: 4583 | K8: =MONTH(B8) -> 10
A9: LN-10008 | B9: 45858 | C9: 2512975 | D9: 8.95 | E9: 48 | F9: Business Loan | G9: Tata Capital | H9: Active | I9: 187426 | J9: 28021 | K9: =MONTH(B9) -> 7
A10: LN-10009 | B10: 45959 | C10: 2171036 | D10: 9.58 | E10: 12 | F10: Business Loan | G10: Northern Arc | H10: Active | I10: 103992 | J10: 34379 | K10: =MONTH(B10) -> 10
A11: LN-10010 | B11: 45752 | C11: 1684888 | D11: 12.61 | E11: 48 | F11: Personal Loan | G11: Northern Arc | H11: Active | I11: 230169 | J11: 31790 | K11: =MONTH(B11) -> 4
A12: LN-10011 | B12: 45796 | C12: 2707996 | D12: 11.8 | E12: 24 | F12: Home Loan | G12: Tata Capital | H12: Active | I12: 319543 | J12: 44197 | K12: =MONTH(B12) -> 5
A13: LN-10012 | B13: 45915 | C13: 160641 | D13: 12.24 | E13: 60 | F13: Business Loan | G13: DMI | H13: Closed | I13: 13108 | J13: 3158 | K13: =MONTH(B13) -> 9
... A301: LN-10300 | B301: 45642 | C301: 2453490 | D301: 11.42 | E301: 48 | F301: Home Loan | G301: Northern Arc | H301: Active | I301: 396933 | J301: 40369 | K301: =MONTH(B301) -> 12

Sheet Actual_Revenue
A1: loan_id | B1: expected_interest_income | C1: expected_processing_fee | D1: actual_interest_received | E1: actual_fee_received | F1: variance_flag | G1: variance_reason
A2: LN-10001 | B2: 305868 | C2: 33318 | D2: 299750 | E2: 33318 | F2: NO
A3: LN-10002 | B3: 70319 | C3: 9347 | D3: 70754 | E3: 9347 | F3: YES | G3: System Error
A4: LN-10003 | B4: 117029 | C4: 12951 | D4: 117029 | E4: 12951 | F4: NO
A5: LN-10004 | B5: 19511 | C5: 24107 | D5: 19511 | E5: 24107 | F5: NO
A6: LN-10005 | B6: 37798 | C6: 2801 | D6: 37798 | E6: 2801 | F6: NO
A7: LN-10006 | B7: 239109 | C7: 45022 | D7: 239109 | E7: 45022 | F7: NO
A8: LN-10007 | B8: 29861 | C8: 4583 | D8: 29861 | E8: 4583 | F8: NO
A9: LN-10008 | B9: 187426 | C9: 28021 | D9: 112455 | E9: 28021 | F9: YES | G9: Partial Payment
A10: LN-10009 | B10: 103992 | C10: 34379 | D10: 103992 | E10: 34379 | F10: NO
A11: LN-10010 | B11: 230169 | C11: 31790 | D11: 230169 | E11: 31790 | F11: NO
A12: LN-10011 | B12: 319543 | C12: 44197 | D12: 335520 | E12: 44197 | F12: YES | G12: Rate Change
A13: LN-10012 | B13: 13108 | C13: 3158 | D13: 13108 | E13: 3158 | F13: NO
A14: LN-10013 | B14: 99978 | C14: 7766 | D14: 79982 | E14: 7766 | F14: YES | G14: Prepayment
A15: LN-10014 | B15: 24454 | C15: 11423 | D15: 24454 | E15: 11423 | F15: NO
A16: LN-10015 | B16: 214052 | C16: 18188 | D16: 214052 | E16: 18006 | F16: NO
A17: LN-10016 | B17: 39348 | C17: 50359 | D17: 39348 | E17: 50359 | F17: NO
A18: LN-10017 | B18: 123653 | C18: 22061 | D18: 123653 | E18: 22061 | F18: NO
A19: LN-10018 | B19: 250333 | C19: 28741 | D19: 245326 | E19: 28741 | F19: NO
A20: LN-10019 | B20: 4129 | C20: 6319 | D20: 4129 | E20: 6319 | F20: NO
A21: LN-10020 | B21: 85614 | C21: 6214 | D21: 85614 | E21: 6214 | F21: NO
A22: LN-10021 | B22: 142107 | C22: 15153 | D22: 142107 | E22: 15153 | F22: NO
A23: LN-10022 | B23: 234424 | C23: 46764 | D23: 234424 | E23: 46764 | F23: NO
A24: LN-10023 | B24: 127873 | C24: 34584 | D24: 127873 | E24: 34584 | F24: NO
A25: LN-10024 | B25: 12976 | C25: 2181 | D25: 12976 | E25: 2181 | F25: NO
A26: LN-10025 | B26: 191863 | C26: 42905 | D26: 191863 | E26: 42905 | F26: NO
A27: LN-10026 | B27: 95442 | C27: 46122 | D27: 100214 | E27: 46122 | F27: YES | G27: Rate Change
A28: LN-10027 | B28: 47945 | C28: 23778 | D28: 28767 | E28: 23778 | F28: YES | G28: Partial Payment
A29: LN-10028 | B29: 294286 | C29: 20065 | D29: 294286 | E29: 20065 | F29: NO
A30: LN-10029 | B30: 79494 | C30: 15919 | D30: 79494 | E30: 15919 | F30: NO
A31: LN-10030 | B31: 268974 | C31: 46733 | D31: 268974 | E31: 46733 | F31: NO
A32: LN-10031 | B32: 179880 | C32: 26239 | D32: 179880 | E32: 26239 | F32: NO
A33: LN-10032 | B33: 11157 | C33: 6020 | D33: 11157 | E33: 6020 | F33: NO
A34: LN-10033 | B34: 52973 | C34: 7560 | D34: 53324 | E34: 7560 | F34: YES | G34: System Error
A35: LN-10034 | B35: 343815 | C35: 25582 | D35: 343815 | E35: 25582 | F35: NO
A36: LN-10035 | B36: 185332 | C36: 39414 | D36: 185332 | E36: 39414 | F36: NO
A37: LN-10036 | B37: 36630 | C37: 3817 | D37: 36630 | E37: 3817 | F37: NO
A38: LN-10037 | B38: 5410 | C38: 3526 | D38: 5410 | E38: 3490 | F38: NO
A39: LN-10038 | B39: 26305 | C39: 7083 | D39: 26305 | E39: 7083 | F39: NO
A40: LN-10039 | B40: 209421 | C40: 24678 | D40: 209421 | E40: 24678 | F40: NO
A41: LN-10040 | B41: 36428 | C41: 45169 | D41: 37193 | E41: 45169 | F41: YES | G41: System Error
A42: LN-10041 | B42: 9988 | C42: 14256 | D42: 9988 | E42: 14256 | F42: NO
A43: LN-10042 | B43: 47871 | C43: 7551 | D43: 47871 | E43: 7551 | F43: NO
A44: LN-10043 | B44: 121865 | C44: 23298 | D44: 121865 | E44: 23298 | F44: NO
A45: LN-10044 | B45: 7409 | C45: 836 | D45: 7409 | E45: 827 | F45: NO
A46: LN-10045 | B46: 131700 | C46: 21296 | D46: 129066 | E46: 21296 | F46: NO
A47: LN-10046 | B47: 330236 | C47: 39103 | D47: 330236 | E47: 39103 | F47: NO
A48: LN-10047 | B48: 250774 | C48: 31030 | D48: 250774 | E48: 31030 | F48: NO
A49: LN-10048 | B49: 22297 | C49: 2929 | D49: 22297 | E49: 2899 | F49: NO
A50: LN-10049 | B50: 86589 | C50: 12846 | D50: 86589 | E50: 12846 | F50: NO
A51: LN-10050 | B51: 138462 | C51: 20006 | D51: 138462 | E51: 20006 | F51: NO
A52: LN-10051 | B52: 82659 | C52: 9574 | D52: 82659 | E52: 9478 | F52: NO
A53: LN-10052 | B53: 429101 | C53: 47290 | D53: 429101 | E53: 47290 | F53: NO
... A69: LN-10068 | B69: 24836 | C69: 29808 | D69: 24836 | E69: 29808 | F69: NO
A70: LN-10069 | B70: 109536 | C70: 25724 | D70: 110210 | E70: 25724 | F70: YES | G70: System Error
A71: LN-10070 | B71: 214000 | C71: 28946 | D71: 214000 | E71: 28946 | F71: NO
A72: LN-10071 | B72: 99386 | C72: 35407 | D72: 99386 | E72: 35407 | F72: NO
A73: LN-10072 | B73: 86672 | C73: 16383 | D73: 86672 | E73: 16383 | F73: NO
A74: LN-10073 | B74: 72302 | C74: 12694 | D74: 72302 | E74: 12694 | F74: NO
A75: LN-10074 | B75: 370391 | C75: 46841 | D75: 370391 | E75: 46841 | F75: NO
A76: LN-10075 | B76: 88094 | C76: 24407 | D76: 92498 | E76: 24407 | F76: YES | G76: Rate Change
A77: LN-10076 | B77: 41646 | C77: 29276 | D77: 43728 | E77: 29276 | F77: YES | G77: Rate Change
A78: LN-10077 | B78: 15658 | C78: 7494 | D78: 15658 | E78: 7494 | F78: NO
A79: LN-10078 | B79: 36280 | C79: 5874 | D79: 36280 | E79: 5874 | F79: NO
A80: LN-10079 | B80: 259543 | C80: 48465 | D80: 259543 | E80: 48465 | F80: NO
A81: LN-10080 | B81: 216946 | C81: 24732 | D81: 216946 | E81: 24732 | F81: NO
A82: LN-10081 | B82: 291821 | C82: 36865 | D82: 291821 | E82: 36496 | F82: NO
A83: LN-10082 | B83: 296219 | C83: 32049 | D83: 290294 | E83: 32049 | F83: NO
A84: LN-10083 | B84: 258220 | C84: 25724 | D84: 258220 | E84: 25724 | F84: NO
A85: LN-10084 | B85: 377310 | C85: 45072 | D85: 377310 | E85: 45072 | F85: NO
A86: LN-10085 | B86: 112602 | C86: 13350 | D86: 67561 | E86: 13350 | F86: YES | G86: Partial Payment
A87: LN-10086 | B87: 250633 | C87: 23570 | D87: 250633 | E87: 23570 | F87: NO
A88: LN-10087 | B88: 53344 | C88: 10168 | D88: 32006 | E88: 10168 | F88: YES | G88: Partial Payment
A89: LN-10088 | B89: 195843 | C89: 34638 | D89: 195843 | E89: 34638 | F89: NO
A90: LN-10089 | B90: 157488 | C90: 13272 | D90: 157488 | E90: 13272 | F90: NO
A91: LN-10090 | B91: 329332 | C91: 39230 | D91: 329332 | E91: 39230 | F91: NO
A92: LN-10091 | B92: 30963 | C92: 23097 | D92: 30343 | E92: 23097 | F92: NO
A93: LN-10092 | B93: 27941 | C93: 4089 | D93: 27941 | E93: 4089 | F93: NO
A94: LN-10093 | B94: 43894 | C94: 53579 | D94: 35115 | E94: 53579 | F94: YES | G94: Prepayment
A95: LN-10094 | B95: 28784 | C95: 2485 | D95: 28784 | E95: 2485 | F95: NO
A96: LN-10095 | B96: 74252 | C96: 9675 | D96: 74252 | E96: 9675 | F96: NO
A97: LN-10096 | B97: 156661 | C97: 18183 | D97: 156661 | E97: 18183 | F97: NO
A98: LN-10097 | B98: 286683 | C98: 45617 | D98: 286683 | E98: 45160 | F98: NO
A99: LN-10098 | B99: 188079 | C99: 18362 | D99: 188079 | E99: 18178 | F99: NO
A100: LN-10099 | B100: 92156 | C100: 56714 | D100: 92156 | E100: 56714 | F100: NO
A101: LN-10100 | B101: 377282 | C101: 41407 | D101: 377282 | E101: 41407 | F101: NO
A102: LN-10101 | B102: 189527 | C102: 18099 | D102: 189527 | E102: 18099 | F102: NO
A103: LN-10102 | B103: 333909 | C103: 41478 | D103: 300518 | E103: 20739 | F103: YES | G103: Waiver Applied
A104: LN-10103 | B104: 57785 | C104: 6250 | D104: 57785 | E104: 6250 | F104: NO
A105: LN-10104 | B105: 337558 | C105: 45339 | D105: 337558 | E105: 45339 | F105: NO
A106: LN-10105 | B106: 78377 | C106: 20750 | D106: 70539 | E106: 10375 | F106: YES | G106: Waiver Applied
A107: LN-10106 | B107: 74702 | C107: 20937 | D107: 74702 | E107: 20937 | F107: NO
A108: LN-10107 | B108: 54682 | C108: 20237 | D108: 54682 | E108: 20237 | F108: NO
A109: LN-10108 | B109: 329725 | C109: 42929 | D109: 329725 | E109: 42929 | F109: NO
A110: LN-10109 | B110: 110219 | C110: 27696 | D110: 110219 | E110: 27696 | F110: NO
A111: LN-10110 | B111: 105195 | C111: 31570 | D111: 105791 | E111: 31570 | F111: YES | G111: System Error
A112: LN-10111 | B112: 249632 | C112: 13013 | D112: 249632 | E112: 13013 | F112: NO
A113: LN-10112 | B113: 371857 | C113: 27925 | D113: 371857 | E113: 27925 | F113: NO
A114: LN-10113 | B114: 348218 | C114: 17661 | D114: 348218 | E114: 17661 | F114: NO
A115: LN-10114 | B115: 99456 | C115: 15935 | D115: 99456 | E115: 15935 | F115: NO
...

Sheet Reconciliation
A1: loan_id | B1: Expected Interest | C1: Actual Interest | D1: Interest Variance | E1: Variance % | F1: Expected Fee | G1: Actual Fee | H1: Fee Variance | I1: Status | J1: Reason
A2: =LMS_Loan_Tape!A2 -> LN-10001 | B2: =VLOOKUP(A2,Actual_Revenue!A:G,2,FALSE) -> 305868 | C2: =VLOOKUP(A2,Actual_Revenue!A:G,4,FALSE) -> 299750 | D2: =B2-C2 -> 6118 | E2: =(D2/B2) -> 0.020002092 | F2: =VLOOKUP(A2,Actual_Revenue!A:G,3,false) -> 33318 | G2: =VLOOKUP(A2,Actual_Revenue!A:G,5,false) -> 33318 | H2: =F2-G2 -> 0 | I2: =IF(AND(D2=0, H2=0),"MATCHED","EXCEPTION") -> EXCEPTION | J2: =VLOOKUP(A2,Actual_Revenue!A:G,7,false) | L2: Summary
A3: =LMS_Loan_Tape!A3 -> LN-10002 | B3: =VLOOKUP(A3,Actual_Revenue!A:G,2,FALSE) -> 70319 | C3: =VLOOKUP(A3,Actual_Revenue!A:G,4,FALSE) -> 70754 | D3: =B3-C3 -> -435 | E3: =(D3/B3) -> -0.0061860948 | F3: =VLOOKUP(A3,Actual_Revenue!A:G,3,false) -> 9347 | G3: =VLOOKUP(A3,Actual_Revenue!A:G,5,false) -> 9347 | H3: =F3-G3 -> 0 | I3: =IF(AND(D3=0, H3=0),"MATCHED","EXCEPTION") -> EXCEPTION | J3: =VLOOKUP(A3,Actual_Revenue!A:G,7,false) -> System Error | L3: Total Expected Revenue | M3: Total Actual Revenue | N3: Total Leakage | O3: Match Rate
A4: =LMS_Loan_Tape!A4 -> LN-10003 | B4: =VLOOKUP(A4,Actual_Revenue!A:G,2,FALSE) -> 117029 | C4: =VLOOKUP(A4,Actual_Revenue!A:G,4,FALSE) -> 117029 | D4: =B4-C4 -> 0 | E4: =(D4/B4) -> 0 | F4: =VLOOKUP(A4,Actual_Revenue!A:G,3,false) -> 12951 | G4: =VLOOKUP(A4,Actual_Revenue!A:G,5,false) -> 12951 | H4: =F4-G4 -> 0 | I4: =IF(AND(D4=0, H4=0),"MATCHED","EXCEPTION") -> MATCHED | J4: =VLOOKUP(A4,Actual_Revenue!A:G,7,false) | L4: =SUM(B:B) + SUM(F:F) -> 50685675 | M4: =SUM(C:C,G:G) -> 49630259 | N4: =L4-M4 -> 1055416 | O4: =COUNTIF(I:I, "MATCHED") / COUNTA(A:A) -> 0.71096346
A5: =LMS_Loan_Tape!A5 -> LN-10004 | B5: =VLOOKUP(A5,Actual_Revenue!A:G,2,FALSE) -> 19511 | C5: =VLOOKUP(A5,Actual_Revenue!A:G,4,FALSE) -> 19511 | D5: =B5-C5 -> 0 | E5: =(D5/B5) -> 0 | F5: =VLOOKUP(A5,Actual_Revenue!A:G,3,false) -> 24107 | G5: =VLOOKUP(A5,Actual_Revenue!A:G,5,false) -> 24107 | H5: =F5-G5 -> 0 | I5: =IF(AND(D5=0, H5=0),"MATCHED","EXCEPTION") -> MATCHED | J5: =VLOOKUP(A5,Actual_Revenue!A:G,7,false)
A6: =LMS_Loan_Tape!A6 -> LN-10005 | B6: =VLOOKUP(A6,Actual_Revenue!A:G,2,FALSE) -> 37798 | C6: =VLOOKUP(A6,Actual_Revenue!A:G,4,FALSE) -> 37798 | D6: =B6-C6 -> 0 | E6: =(D6/B6) -> 0 | F6: =VLOOKUP(A6,Actual_Revenue!A:G,3,false) -> 2801 | G6: =VLOOKUP(A6,Actual_Revenue!A:G,5,false) -> 2801 | H6: =F6-G6 -> 0 | I6: =IF(AND(D6=0, H6=0),"MATCHED","EXCEPTION") -> MATCHED | J6: =VLOOKUP(A6,Actual_Revenue!A:G,7,false)
A7: =LMS_Loan_Tape!A7 -> LN-10006 | B7: =VLOOKUP(A7,Actual_Revenue!A:G,2,FALSE) -> 239109 | C7: =VLOOKUP(A7,Actual_Revenue!A:G,4,FALSE) -> 239109 | D7: =B7-C7 -> 0 | E7: =(D7/B7) -> 0 | F7: =VLOOKUP(A7,Actual_Revenue!A:G,3,false) -> 45022 | G7: =VLOOKUP(A7,Actual_Revenue!A:G,5,false) -> 45022 | H7: =F7-G7 -> 0 | I7: =IF(AND(D7=0, H7=0),"MATCHED","EXCEPTION") -> MATCHED | J7: =VLOOKUP(A7,Actual_Revenue!A:G,7,false)
A8: =LMS_Loan_Tape!A8 -> LN-10007 | B8: =VLOOKUP(A8,Actual_Revenue!A:G,2,FALSE) -> 29861 | C8: =VLOOKUP(A8,Actual_Revenue!A:G,4,FALSE) -> 29861 | D8: =B8-C8 -> 0 | E8: =(D8/B8) -> 0 | F8: =VLOOKUP(A8,Actual_Revenue!A:G,3,false) -> 4583 | G8: =VLOOKUP(A8,Actual_Revenue!A:G,5,false) -> 4583 | H8: =F8-G8 -> 0 | I8: =IF(AND(D8=0, H8=0),"MATCHED","EXCEPTION") -> MATCHED | J8: =VLOOKUP(A8,Actual_Revenue!A:G,7,false)
A9: =LMS_Loan_Tape!A9 -> LN-10008 | B9: =VLOOKUP(A9,Actual_Revenue!A:G,2,FALSE) -> 187426 | C9: =VLOOKUP(A9,Actual_Revenue!A:G,4,FALSE) -> 112455 | D9: =B9-C9 -> 74971 | E9: =(D9/B9) -> 0.4000032 | F9: =VLOOKUP(A9,Actual_Revenue!A:G,3,false) -> 28021 | G9: =VLOOKUP(A9,Actual_Revenue!A:G,5,false) -> 28021 | H9: =F9-G9 -> 0 | I9: =IF(AND(D9=0, H9=0),"MATCHED","EXCEPTION") -> EXCEPTION | J9: =VLOOKUP(A9,Actual_Revenue!A:G,7,false) -> Partial Payment
A10: =LMS_Loan_Tape!A10 -> LN-10009 | B10: =VLOOKUP(A10,Actual_Revenue!A:G,2,FALSE) -> 103992 | C10: =VLOOKUP(A10,Actual_Revenue!A:G,4,FALSE) -> 103992 | D10: =B10-C10 -> 0 | E10: =(D10/B10) -> 0 | F10: =VLOOKUP(A10,Actual_Revenue!A:G,3,false) -> 34379 | G10: =VLOOKUP(A10,Actual_Revenue!A:G,5,false) -> 34379 | H10: =F10-G10 -> 0 | I10: =IF(AND(D10=0, H10=0),"MATCHED","EXCEPTION") -> MATCHED | J10: =VLOOKUP(A10,Actual_Revenue!A:G,7,false)
A11: =LMS_Loan_Tape!A11 -> LN-10010 | B11: =VLOOKUP(A11,Actual_Revenue!A:G,2,FALSE) -> 230169 | C11: =VLOOKUP(A11,Actual_Revenue!A:G,4,FALSE) -> 230169 | D11: =B11-C11 -> 0 | E11: =(D11/B11) -> 0 | F11: =VLOOKUP(A11,Actual_Revenue!A:G,3,false) -> 31790 | G11: =VLOOKUP(A11,Actual_Revenue!A:G,5,false) -> 31790 | H11: =F11-G11 -> 0 | I11: =IF(AND(D11=0, H11=0),"MATCHED","EXCEPTION") -> MATCHED | J11: =VLOOKUP(A11,Actual_Revenue!A:G,7,false)
A12: =LMS_Loan_Tape!A12 -> LN-10011 | B12: =VLOOKUP(A12,Actual_Revenue!A:G,2,FALSE) -> 319543 | C12: =VLOOKUP(A12,Actual_Revenue!A:G,4,FALSE) -> 335520 | D12: =B12-C12 -> -15977 | E12: =(D12/B12) -> -0.049999531 | F12: =VLOOKUP(A12,Actual_Revenue!A:G,3,false) -> 44197 | G12: =VLOOKUP(A12,Actual_Revenue!A:G,5,false) -> 44197 | H12: =F12-G12 -> 0 | I12: =IF(AND(D12=0, H12=0),"MATCHED","EXCEPTION") -> EXCEPTION | J12: =VLOOKUP(A12,Actual_Revenue!A:G,7,false) -> Rate Change
A13: =LMS_Loan_Tape!A13 -> LN-10012 | B13: =VLOOKUP(A13,Actual_Revenue!A:G,2,FALSE) -> 13108 | C13: =VLOOKUP(A13,Actual_Revenue!A:G,4,FALSE) -> 13108 | D13: =B13-C13 -> 0 | E13: =(D13/B13) -> 0 | F13: =VLOOKUP(A13,Actual_Revenue!A:G,3,false) -> 3158 | G13: =VLOOKUP(A13,Actual_Revenue!A:G,5,false) -> 3158 | H13: =F13-G13 -> 0 | I13: =IF(AND(D13=0, H13=0),"MATCHED","EXCEPTION") -> MATCHED | J13: =VLOOKUP(A13,Actual_Revenue!A:G,7,false)
A14: =LMS_Loan_Tape!A14 -> LN-10013 | B14: =VLOOKUP(A14,Actual_Revenue!A:G,2,FALSE) -> 99978 | C14: =VLOOKUP(A14,Actual_Revenue!A:G,4,FALSE) -> 79982 | D14: =B14-C14 -> 19996 | E14: =(D14/B14) -> 0.200004 | F14: =VLOOKUP(A14,Actual_Revenue!A:G,3,false) -> 7766 | G14: =VLOOKUP(A14,Actual_Revenue!A:G,5,false) -> 7766 | H14: =F14-G14 -> 0 | I14: =IF(AND(D14=0, H14=0),"MATCHED","EXCEPTION") -> EXCEPTION | J14: =VLOOKUP(A14,Actual_Revenue!A:G,7,false) -> Prepayment
A15: =LMS_Loan_Tape!A15 -> LN-10014 | B15: =VLOOKUP(A15,Actual_Revenue!A:G,2,FALSE) -> 24454 | C15: =VLOOKUP(A15,Actual_Revenue!A:G,4,FALSE) -> 24454 | D15: =B15-C15 -> 0 | E15: =(D15/B15) -> 0 | F15: =VLOOKUP(A15,Actual_Revenue!A:G,3,false) -> 11423 | G15: =VLOOKUP(A15,Actual_Revenue!A:G,5,false) -> 11423 | H15: =F15-G15 -> 0 | I15: =IF(AND(D15=0, H15=0),"MATCHED","EXCEPTION") -> MATCHED | J15: =VLOOKUP(A15,Actual_Revenue!A:G,7,false)
A16: =LMS_Loan_Tape!A16 -> LN-10015 | B16: =VLOOKUP(A16,Actual_Revenue!A:G,2,FALSE) -> 214052 | C16: =VLOOKUP(A16,Actual_Revenue!A:G,4,FALSE) -> 214052 | D16: =B16-C16 -> 0 | E16: =(D16/B16) -> 0 | F16: =VLOOKUP(A16,Actual_Revenue!A:G,3,false) -> 18188 | G16: =VLOOKUP(A16,Actual_Revenue!A:G,5,false) -> 18006 | H16: =F16-G16 -> 182 | I16: =IF(AND(D16=0, H16=0),"MATCHED","EXCEPTION") -> EXCEPTION | J16: =VLOOKUP(A16,Actual_Revenue!A:G,7,false)
... A301: =LMS_Loan_Tape!A301 -> LN-10300 | B301: =VLOOKUP(A301,Actual_Revenue!A:G,2,FALSE) -> 396933 | C301: =VLOOKUP(A301,Actual_Revenue!A:G,4,FALSE) -> 396933 | D301: =B301-C301 -> 0 | E301: =(D301/B301) -> 0 | F301: =VLOOKUP(A301,Actual_Revenue!A:G,3,false) -> 40369 | G301: =VLOOKUP(A301,Actual_Revenue!A:G,5,false) -> 40369 | H301: =F301-G301 -> 0 | I301: =IF(AND(D301=0, H301=0),"MATCHED","EXCEPTION") -> MATCHED | J301: =VLOOKUP(A301,Actual_Revenue!A:G,7,false)
A302: =LMS_Loan_Tape!A302
A303: =LMS_Loan_Tape!A303
A304: =LMS_Loan_Tape!A304
A305: =LMS_Loan_Tape!A305
A306: =LMS_Loan_Tape!A306
A307: =LMS_Loan_Tape!A307
A308: =LMS_Loan_Tape!A308

Sheet Exception_Report
A1: loan_id | B1: Expected Interest | C1: Actual Interest | D1: Interest Variance | E1: Variance % | F1: Expected Fee | G1: Actual Fee | H1: Fee Variance | I1: Status | J1: Reason | K1: Action Required | L1: Lender | M1: Total variance | N1: product_type | O1: month | P1: Reason | Q1: Count of Loans | R1: Total Variance
A2: =IFERROR(__xludf.DUMMYFUNCTION("FILTER(Reconciliation!A:J, Reconciliation!I:I = ""EXCEPTION"")"),"LN-10001") -> LN-10001 | B2: =IFERROR(__xludf.DUMMYFUNCTION("""COMPUTED_VALUE"""),305868.0) -> 305868 | C2: =IFERROR(__xludf.DUMMYFUNCTION("""COMPUTED_VALUE"""),299750.0) -> 299750 | D2: =IFERROR(__xludf.DUMMYFUNCTION("""COMPUTED_VALUE"""),6118.0) -> 6118 | E2: =IFERROR(__xludf.DUMMYFUNCTION("""COMPUTED_VALUE"""),0.02000209240587443) -> 0.020002092 | F2: =IFERROR(__xludf.DUMMYFUNCTION("""COMPUTED_VALUE"""),33318.0) -> 33318 | G2: =IFERROR(__xludf.DUMMYFUNCTION("""COMPUTED_VALUE"""),33318.0) -> 33318 | H2: =IFERROR(__xludf.DUMMYFUNCTION("""COMPUTED_VALUE"""),0.0) -> 0 | I2: =IFERROR(__xludf.DUMMYFUNCTION("""COMPUTED_VALUE"""),"EXCEPTION") -> EXCEPTION | K2: =IFS(J2="Prepayment", "Update schedule, recalculate interest",J2="System Error", "Escalate to tech team",J2="Waiver Applied", "Verify approval, update ledger",J2="Partial Payment", "Contact customer for balance",J2="Rate Change", "Update loan agreement",J2="", "" ) | L2: =VLOOKUP(A2,LMS_Loan_Tape!A:Z,7,FALSE) -> DMI | M2: =D2+H2 -> 6118 | N2: =VLOOKUP(A2,LMS_Loan_Tape!A:Z,6,FALSE) -> Personal Loan | O2: =VLOOKUP(A2, LMS_Loan_Tape!A1:Z1000,11,false) -> 3 | P2: System Error | Q2: =COUNTIF(J:J,"System Error") -> 12 | R2: =SUMIF(J:J,"System Error",D:D)+SUMIF(J:J,"System Error",H:H) -> -6730
A3: =IFERROR(__xludf.DUMMYFUNCTION("""COMPUTED_VALUE"""),"LN-10002") -> LN-10002 | B3: =IFERROR(__xludf.DUMMYFUNCTION("""COMPUTED_VALUE"""),70319.0) -> 70319 | C3: =IFERROR(__xludf.DUMMYFUNCTION("""COMPUTED_VALUE"""),70754.0) -> 70754 | D3: =IFERROR(__xludf.DUMMYFUNCTION("""COMPUTED_VALUE"""),-435.0) -> -435 | E3: =IFERROR(__xludf.DUMMYFUNCTION("""COMPUTED_VALUE"""),-0.006186094796569917) -> -0.0061860948 | F3: =IFERROR(__xludf.DUMMYFUNCTION("""COMPUTED_VALUE"""),9347.0) -> 9347 | G3: =IFERROR(__xludf.DUMMYFUNCTION("""COMPUTED_VALUE"""),9347.0) -> 9347 | H3: =IFERROR(__xludf.DUMMYFUNCTION("""COMPUTED_VALUE"""),0.0) -> 0 | I3: =IFERROR(__xludf.DUMMYFUNCTION("""COMPUTED_VALUE"""),"EXCEPTION") -> EXCEPTION | J3: =IFERROR(__xludf.DUMMYFUNCTION("""COMPUTED_VALUE"""),"System Error") -> System Error | K3: =IFS(J3="Prepayment", "Update schedule, recalculate interest",J3="System Error", "Escalate to tech team",J3="Waiver Applied", "Verify approval, update ledger",J3="Partial Payment", "Contact customer for balance",J3="Rate Change", "Update loan agreement",J3="", "" ) -> Escalate to tech team | L3: =VLOOKUP(A3,LMS_Loan_Tape!A:Z,7,FALSE) -> Tata Capital | M3: =D3+H3 -> -435 | N3: =VLOOKUP(A3,LMS_Loan_Tape!A:Z,6,FALSE) -> Business Loan | O3: =VLOOKUP(A3, LMS_Loan_Tape!A2:Z1001,11,false) -> 6 | P3: Partial Payment | Q3: =COUNTIF(J:J,"Partial Payment") -> 12 | R3: =SUMIF(J:J,"Partial Payment",D:D)+SUMIF(J:J,"Partial Payment",H:H) -> 856935
A4: =IFERROR(__xludf.DUMMYFUNCTION("""COMPUTED_VALUE"""),"LN-10008") -> LN-10008 | B4: =IFERROR(__xludf.DUMMYFUNCTION("""COMPUTED_VALUE"""),187426.0) -> 187426 | C4: =IFERROR(__xludf.DUMMYFUNCTION("""COMPUTED_VALUE"""),112455.0) -> 112455 | D4: =IFERROR(__xludf.DUMMYFUNCTION("""COMPUTED_VALUE"""),74971.0) -> 74971 | E4: =IFERROR(__xludf.DUMMYFUNCTION("""COMPUTED_VALUE"""),0.400003201263432) -> 0.4000032 | F4: =IFERROR(__xludf.DUMMYFUNCTION("""COMPUTED_VALUE"""),28021.0) -> 28021 | G4: =IFERROR(__xludf.DUMMYFUNCTION("""COMPUTED_VALUE"""),28021.0) -> 28021 | H4: =IFERROR(__xludf.DUMMYFUNCTION("""COMPUTED_VALUE"""),0.0) -> 0 | I4: =IFERROR(__xludf.DUMMYFUNCTION("""COMPUTED_VALUE"""),"EXCEPTION") -> EXCEPTION | J4: =IFERROR(__xludf.DUMMYFUNCTION("""COMPUTED_VALUE"""),"Partial Payment") -> Partial Payment | K4: =IFS(J4="Prepayment", "Update schedule, recalculate interest",J4="System Error", "Escalate to tech team",J4="Waiver Applied", "Verify approval, update ledger",J4="Partial Payment", "Contact customer for balance",J4="Rate Change", "Update loan agreement",J4="", "" ) -> Contact customer for balance | L4: =VLOOKUP(A4,LMS_Loan_Tape!A:Z,7,FALSE) -> Tata Capital | M4: =D4+H4 -> 74971 | N4: =VLOOKUP(A4,LMS_Loan_Tape!A:Z,6,FALSE) -> Business Loan | O4: =VLOOKUP(A4, LMS_Loan_Tape!A3:Z1002,11,false) -> 7 | P4: Rate Change | Q4: =COUNTIF(J:J,"Rate Change") -> 9 | R4: =SUMIF(J:J,"Rate Change",D:D)+SUMIF(J:J,"Rate Change",H:H) -> -57604
A5: =IFERROR(__xludf.DUMMYFUNCTION("""COMPUTED_VALUE"""),"LN-10011") -> LN-10011 | B5: =IFERROR(__xludf.DUMMYFUNCTION("""COMPUTED_VALUE"""),319543.0) -> 319543 | C5: =IFERROR(__xludf.DUMMYFUNCTION("""COMPUTED_VALUE"""),335520.0) -> 335520 | D5: =IFERROR(__xludf.DUMMYFUNCTION("""COMPUTED_VALUE"""),-15977.0) -> -15977 | E5: =IFERROR(__xludf.DUMMYFUNCTION("""COMPUTED_VALUE"""),-0.04999953057960901) -> -0.049999531 | F5: =IFERROR(__xludf.DUMMYFUNCTION("""COMPUTED_VALUE"""),44197.0) -> 44197 | G5: =IFERROR(__xludf.DUMMYFUNCTION("""COMPUTED_VALUE"""),44197.0) -> 44197 | H5: =IFERROR(__xludf.DUMMYFUNCTION("""COMPUTED_VALUE"""),0.0) -> 0 | I5: =IFERROR(__xludf.DUMMYFUNCTION("""COMPUTED_VALUE"""),"EXCEPTION") -> EXCEPTION | J5: =IFERROR(__xludf.DUMMYFUNCTION("""COMPUTED_VALUE"""),"Rate Change") -> Rate Change | K5: =IFS(J5="Prepayment", "Update schedule, recalculate interest",J5="System Error", "Escalate to tech team",J5="Waiver Applied", "Verify approval, update ledger",J5="Partial Payment", "Contact customer for balance",J5="Rate Change", "Update loan agreement",J5="", "" ) -> Update loan agreement | L5: =VLOOKUP(A5,LMS_Loan_Tape!A:Z,7,FALSE) -> Tata Capital | M5: =D5+H5 -> -15977 | N5: =VLOOKUP(A5,LMS_Loan_Tape!A:Z,6,FALSE) -> Home Loan | O5: =VLOOKUP(A5, LMS_Loan_Tape!A4:Z1003,11,false) -> 5 | P5: Prepayment | Q5: =COUNTIF(J:J,"Prepayment") -> 4 | R5: =SUMIF(J:J,"Prepayment",D:D)+SUMIF(J:J,"Prepayment",H:H) -> 42022
A6: =IFERROR(__xludf.DUMMYFUNCTION("""COMPUTED_VALUE"""),"LN-10013") -> LN-10013 | B6: =IFERROR(__xludf.DUMMYFUNCTION("""COMPUTED_VALUE"""),99978.0) -> 99978 | C6: =IFERROR(__xludf.DUMMYFUNCTION("""COMPUTED_VALUE"""),79982.0) -> 79982 | D6: =IFERROR(__xludf.DUMMYFUNCTION("""COMPUTED_VALUE"""),19996.0) -> 19996 | E6: =IFERROR(__xludf.DUMMYFUNCTION("""COMPUTED_VALUE"""),0.20000400088019366) -> 0.200004 | F6: =IFERROR(__xludf.DUMMYFUNCTION("""COMPUTED_VALUE"""),7766.0) -> 7766 | G6: =IFERROR(__xludf.DUMMYFUNCTION("""COMPUTED_VALUE"""),7766.0) -> 7766 | H6: =IFERROR(__xludf.DUMMYFUNCTION("""COMPUTED_VALUE"""),0.0) -> 0 | I6: =IFERROR(__xludf.DUMMYFUNCTION("""COMPUTED_VALUE"""),"EXCEPTION") -> EXCEPTION | J6: =IFERROR(__xludf.DUMMYFUNCTION("""COMPUTED_VALUE"""),"Prepayment") -> Prepayment | K6: =IFS(J6="Prepayment", "Update schedule, recalculate interest",J6="System Error", "Escalate to tech team",J6="Waiver Applied", "Verify approval, update ledger",J6="Partial Payment", "Contact customer for balance",J6="Rate Change", "Update loan agreement",J6="", "" ) -> Update schedule, recalculate interest | L6: =VLOOKUP(A6,LMS_Loan_Tape!A:Z,7,FALSE) -> DMI | M6: =D6+H6 -> 19996 | N6: =VLOOKUP(A6,LMS_Loan_Tape!A:Z,6,FALSE) -> Gold Loan | O6: =VLOOKUP(A6, LMS_Loan_Tape!A5:Z1004,11,false) -> 3 | P6: Waiver Applied | Q6: =COUNTIF(J:J,"Waiver Applied") -> 9 | R6: =SUMIF(J:J,"Waiver Applied",D:D)+SUMIF(J:J,"Waiver Applied",H:H) -> 162015
A7: =IFERROR(__xludf.DUMMYFUNCTION("""COMPUTED_VALUE"""),"LN-10015") -> LN-10015 | B7: =IFERROR(__xludf.DUMMYFUNCTION("""COMPUTED_VALUE"""),214052.0) -> 214052 | C7: =IFERROR(__xludf.DUMMYFUNCTION("""COMPUTED_VALUE"""),214052.0) -> 214052 | D7: =IFERROR(__xludf.DUMMYFUNCTION("""COMPUTED_VALUE"""),0.0) -> 0 | E7: =IFERROR(__xludf.DUMMYFUNCTION("""COMPUTED_VALUE"""),0.0) -> 0 | F7: =IFERROR(__xludf.DUMMYFUNCTION("""COMPUTED_VALUE"""),18188.0) -> 18188 | G7: =IFERROR(__xludf.DUMMYFUNCTION("""COMPUTED_VALUE"""),18006.0) -> 18006 | H7: =IFERROR(__xludf.DUMMYFUNCTION("""COMPUTED_VALUE"""),182.0) -> 182 | I7: =IFERROR(__xludf.DUMMYFUNCTION("""COMPUTED_VALUE"""),"EXCEPTION") -> EXCEPTION | K7: =IFS(J7="Prepayment", "Update schedule, recalculate interest",J7="System Error", "Escalate to tech team",J7="Waiver Applied", "Verify approval, update ledger",J7="Partial Payment", "Contact customer for balance",J7="Rate Change", "Update loan agreement",J7="", "" ) | L7: =VLOOKUP(A7,LMS_Loan_Tape!A:Z,7,FALSE) -> Piramal | M7: =D7+H7 -> 182 | N7: =VLOOKUP(A7,LMS_Loan_Tape!A:Z,6,FALSE) -> Gold Loan | O7: =VLOOKUP(A7, LMS_Loan_Tape!A6:Z1005,11,false) -> 4
A8: =IFERROR(__xludf.DUMMYFUNCTION("""COMPUTED_VALUE"""),"LN-10018") -> LN-10018 | B8: =IFERROR(__xludf.DUMMYFUNCTION("""COMPUTED_VALUE"""),250333.0) -> 250333 | C8: =IFERROR(__xludf.DUMMYFUNCTION("""COMPUTED_VALUE"""),245326.0) -> 245326 | D8: =IFERROR(__xludf.DUMMYFUNCTION("""COMPUTED_VALUE"""),5007.0) -> 5007 | E8: =IFERROR(__xludf.DUMMYFUNCTION("""COMPUTED_VALUE"""),0.020001358190889735) -> 0.020001358 | F8: =IFERROR(__xludf.DUMMYFUNCTION("""COMPUTED_VALUE"""),28741.0) -> 28741 | G8: =IFERROR(__xludf.DUMMYFUNCTION("""COMPUTED_VALUE"""),28741.0) -> 28741 | H8: =IFERROR(__xludf.DUMMYFUNCTION("""COMPUTED_VALUE"""),0.0) -> 0 | I8: =IFERROR(__xludf.DUMMYFUNCTION("""COMPUTED_VALUE"""),"EXCEPTION") -> EXCEPTION | K8: =IFS(J8="Prepayment", "Update schedule, recalculate interest",J8="System Error", "Escalate to tech team",J8="Waiver Applied", "Verify approval, update ledger",J8="Partial Payment", "Contact customer for balance",J8="Rate Change", "Update loan agreement",J8="", "" ) | L8: =VLOOKUP(A8,LMS_Loan_Tape!A:Z,7,FALSE) -> Northern Arc | M8: =D8+H8 -> 5007 | N8: =VLOOKUP(A8,LMS_Loan_Tape!A:Z,6,FALSE) -> Personal Loan | O8: =VLOOKUP(A8, LMS_Loan_Tape!A7:Z1006,11,false) -> 5
A9: =IFERROR(__xludf.DUMMYFUNCTION("""COMPUTED_VALUE"""),"LN-10026") -> LN-10026 | B9: =IFERROR(__xludf.DUMMYFUNCTION("""COMPUTED_VALUE"""),95442.0) -> 95442 | C9: =IFERROR(__xludf.DUMMYFUNCTION("""COMPUTED_VALUE"""),100214.0) -> 100214 | D9: =IFERROR(__xludf.DUMMYFUNCTION("""COMPUTED_VALUE"""),-4772.0) -> -4772 | E9: =IFERROR(__xludf.DUMMYFUNCTION("""COMPUTED_VALUE"""),-0.049998952243247206) -> -0.049998952 | F9: =IFERROR(__xludf.DUMMYFUNCTION("""COMPUTED_VALUE"""),46122.0) -> 46122 | G9: =IFERROR(__xludf.DUMMYFUNCTION("""COMPUTED_VALUE"""),46122.0) -> 46122 | H9: =IFERROR(__xludf.DUMMYFUNCTION("""COMPUTED_VALUE"""),0.0) -> 0 | I9: =IFERROR(__xludf.DUMMYFUNCTION("""COMPUTED_VALUE"""),"EXCEPTION") -> EXCEPTION | J9: =IFERROR(__xludf.DUMMYFUNCTION("""COMPUTED_VALUE"""),"Rate Change") -> Rate Change | K9: =IFS(J9="Prepayment", "Update schedule, recalculate interest",J9="System Error", "Escalate to tech team",J9="Waiver Applied", "Verify approval, update ledger",J9="Partial Payment", "Contact customer for balance",J9="Rate Change", "Update loan agreement",J9="", "" ) -> Update loan agreement | L9: =VLOOKUP(A9,LMS_Loan_Tape!A:Z,7,FALSE) -> DMI | M9: =D9+H9 -> -4772 | N9: =VLOOKUP(A9,LMS_Loan_Tape!A:Z,6,FALSE) -> Gold Loan | O9: =VLOOKUP(A9, LMS_Loan_Tape!A8:Z1007,11,false) -> 1
A10: =IFERROR(__xludf.DUMMYFUNCTION("""COMPUTED_VALUE"""),"LN-10027") -> LN-10027 | B10: =IFERROR(__xludf.DUMMYFUNCTION("""COMPUTED_VALUE"""),47945.0) -> 47945 | C10: =IFERROR(__xludf.DUMMYFUNCTION("""COMPUTED_VALUE"""),28767.0) -> 28767 | D10: =IFERROR(__xludf.DUMMYFUNCTION("""COMPUTED_VALUE"""),19178.0) -> 19178 | E10: =IFERROR(__xludf.DUMMYFUNCTION("""COMPUTED_VALUE"""),0.4) -> 0.4 | F10: =IFERROR(__xludf.DUMMYFUNCTION("""COMPUTED_VALUE"""),23778.0) -> 23778 | G10: =IFERROR(__xludf.DUMMYFUNCTION("""COMPUTED_VALUE"""),23778.0) -> 23778 | H10: =IFERROR(__xludf.DUMMYFUNCTION("""COMPUTED_VALUE"""),0.0) -> 0 | I10: =IFERROR(__xludf.DUMMYFUNCTION("""COMPUTED_VALUE"""),"EXCEPTION") -> EXCEPTION | J10: =IFERROR(__xludf.DUMMYFUNCTION("""COMPUTED_VALUE"""),"Partial Payment") -> Partial Payment | K10: =IFS(J10="Prepayment", "Update schedule, recalculate interest",J10="System Error", "Escalate to tech team",J10="Waiver Applied", "Verify approval, update ledger",J10="Partial Payment", "Contact customer for balance",J10="Rate Change", "Update loan agreement",J10="", "" ) -> Contact customer for balance | L10: =VLOOKUP(A10,LMS_Loan_Tape!A:Z,7,FALSE) -> Piramal | M10: =D10+H10 -> 19178 | N10: =VLOOKUP(A10,LMS_Loan_Tape!A:Z,6,FALSE) -> Business Loan | O10: =VLOOKUP(A10, LMS_Loan_Tape!A9:Z1008,11,false) -> 2
A11: =IFERROR(__xludf.DUMMYFUNCTION("""COMPUTED_VALUE"""),"LN-10033") -> LN-10033 | B11: =IFERROR(__xludf.DUMMYFUNCTION("""COMPUTED_VALUE"""),52973.0) -> 52973 | C11: =IFERROR(__xludf.DUMMYFUNCTION("""COMPUTED_VALUE"""),53324.0) -> 53324 | D11: =IFERROR(__xludf.DUMMYFUNCTION("""COMPUTED_VALUE"""),-351.0) -> -351 | E11: =IFERROR(__xludf.DUMMYFUNCTION("""COMPUTED_VALUE"""),-0.006626017027542333) -> -0.006626017 | F11: =IFERROR(__xludf.DUMMYFUNCTION("""COMPUTED_VALUE"""),7560.0) -> 7560 | G11: =IFERROR(__xludf.DUMMYFUNCTION("""COMPUTED_VALUE"""),7560.0) -> 7560 | H11: =IFERROR(__xludf.DUMMYFUNCTION("""COMPUTED_VALUE"""),0.0) -> 0 | I11: =IFERROR(__xludf.DUMMYFUNCTION("""COMPUTED_VALUE"""),"EXCEPTION") -> EXCEPTION | J11: =IFERROR(__xludf.DUMMYFUNCTION("""COMPUTED_VALUE"""),"System Error") -> System Error | K11: =IFS(J11="Prepayment", "Update schedule, recalculate interest",J11="System Error", "Escalate to tech team",J11="Waiver Applied", "Verify approval, update ledger",J11="Partial Payment", "Contact customer for balance",J11="Rate Change", "Update loan agreement",J11="", "" ) -> Escalate to tech team | L11: =VLOOKUP(A11,LMS_Loan_Tape!A:Z,7,FALSE) -> DMI | M11: =D11+H11 -> -351 | N11: =VLOOKUP(A11,LMS_Loan_Tape!A:Z,6,FALSE) -> Home Loan | O11: =VLOOKUP(A11, LMS_Loan_Tape!A10:Z1009,11,false) -> 4
A12: =IFERROR(__xludf.DUMMYFUNCTION("""COMPUTED_VALUE"""),"LN-10037") -> LN-10037 | B12: =IFERROR(__xludf.DUMMYFUNCTION("""COMPUTED_VALUE"""),5410.0) -> 5410 | C12: =IFERROR(__xludf.DUMMYFUNCTION("""COMPUTED_VALUE"""),5410.0) -> 5410 | D12: =IFERROR(__xludf.DUMMYFUNCTION("""COMPUTED_VALUE"""),0.0) -> 0 | E12: =IFERROR(__xludf.DUMMYFUNCTION("""COMPUTED_VALUE"""),0.0) -> 0 | F12: =IFERROR(__xludf.DUMMYFUNCTION("""COMPUTED_VALUE"""),3526.0) -> 3526 | G12: =IFERROR(__xludf.DUMMYFUNCTION("""COMPUTED_VALUE"""),3490.0) -> 3490 | H12: =IFERROR(__xludf.DUMMYFUNCTION("""COMPUTED_VALUE"""),36.0) -> 36 | I12: =IFERROR(__xludf.DUMMYFUNCTION("""COMPUTED_VALUE"""),"EXCEPTION") -> EXCEPTION | K12: =IFS(J12="Prepayment", "Update schedule, recalculate interest",J12="System Error", "Escalate to tech team",J12="Waiver Applied", "Verify approval, update ledger",J12="Partial Payment", "Contact customer for balance",J12="Rate Change", "Update loan agreement",J12="", "" ) | L12: =VLOOKUP(A12,LMS_Loan_Tape!A:Z,7,FALSE) -> Piramal | M12: =D12+H12 -> 36 | N12: =VLOOKUP(A12,LMS_Loan_Tape!A:Z,6,FALSE) -> Personal Loan | O12: =VLOOKUP(A12, LMS_Loan_Tape!A11:Z1010,11,false) -> 3
A13: =IFERROR(__xludf.DUMMYFUNCTION("""COMPUTED_VALUE"""),"LN-10040") -> LN-10040 | B13: =IFERROR(__xludf.DUMMYFUNCTION("""COMPUTED_VALUE"""),36428.0) -> 36428 | C13: =IFERROR(__xludf.DUMMYFUNCTION("""COMPUTED_VALUE"""),37193.0) -> 37193 | D13: =IFERROR(__xludf.DUMMYFUNCTION("""COMPUTED_VALUE"""),-765.0) -> -765 | E13: =IFERROR(__xludf.DUMMYFUNCTION("""COMPUTED_VALUE"""),-0.02100032941693203) -> -0.021000329 | F13: =IFERROR(__xludf.DUMMYFUNCTION("""COMPUTED_VALUE"""),45169.0) -> 45169 | G13: =IFERROR(__xludf.DUMMYFUNCTION("""COMPUTED_VALUE"""),45169.0) -> 45169 | H13: =IFERROR(__xludf.DUMMYFUNCTION("""COMPUTED_VALUE"""),0.0) -> 0 | I13: =IFERROR(__xludf.DUMMYFUNCTION("""COMPUTED_VALUE"""),"EXCEPTION") -> EXCEPTION | J13: =IFERROR(__xludf.DUMMYFUNCTION("""COMPUTED_VALUE"""),"System Error") -> System Error | K13: =IFS(J13="Prepayment", "Update schedule, recalculate interest",J13="System Error", "Escalate to tech team",J13="Waiver Applied", "Verify approval, update ledger",J13="Partial Payment", "Contact customer for balance",J13="Rate Change", "Update loan agreement",J13="", "" ) -> Escalate to tech team | L13: =VLOOKUP(A13,LMS_Loan_Tape!A:Z,7,FALSE) -> DMI | M13: =D13+H13 -> -765 | N13: =VLOOKUP(A13,LMS_Loan_Tape!A:Z,6,FALSE) -> Personal Loan | O13: =VLOOKUP(A13, LMS_Loan_Tape!A12:Z1011,11,false) -> 3
A14: =IFERROR(__xludf.DUMMYFUNCTION("""COMPUTED_VALUE"""),"LN-10044") -> LN-10044 | B14: =IFERROR(__xludf.DUMMYFUNCTION("""COMPUTED_VALUE"""),7409.0) -> 7409 | C14: =IFERROR(__xludf.DUMMYFUNCTION("""COMPUTED_VALUE"""),7409.0) -> 7409 | D14: =IFERROR(__xludf.DUMMYFUNCTION("""COMPUTED_VALUE"""),0.0) -> 0 | E14: =IFERROR(__xludf.DUMMYFUNCTION("""COMPUTED_VALUE"""),0.0) -> 0 | F14: =IFERROR(__xludf.DUMMYFUNCTION("""COMPUTED_VALUE"""),836.0) -> 836 | G14: =IFERROR(__xludf.DUMMYFUNCTION("""COMPUTED_VALUE"""),827.0) -> 827 | H14: =IFERROR(__xludf.DUMMYFUNCTION("""COMPUTED_VALUE"""),9.0) -> 9 | I14: =IFERROR(__xludf.DUMMYFUNCTION("""COMPUTED_VALUE"""),"EXCEPTION") -> EXCEPTION | K14: =IFS(J14="Prepayment", "Update schedule, recalculate interest",J14="System Error", "Escalate to tech team",J14="Waiver Applied", "Verify approval, update ledger",J14="Partial Payment", "Contact customer for balance",J14="Rate Change", "Update loan agreement",J14="", "" ) | L14: =VLOOKUP(A14,LMS_Loan_Tape!A:Z,7,FALSE) -> DMI | M14: =D14+H14 -> 9 | N14: =VLOOKUP(A14,LMS_Loan_Tape!A:Z,6,FALSE) -> Home Loan | O14: =VLOOKUP(A14, LMS_Loan_Tape!A13:Z1012,11,false) -> 1
A15: =IFERROR(__xludf.DUMMYFUNCTION("""COMPUTED_VALUE"""),"LN-10045") -> LN-10045 | B15: =IFERROR(__xludf.DUMMYFUNCTION("""COMPUTED_VALUE"""),131700.0) -> 131700 | C15: =IFERROR(__xludf.DUMMYFUNCTION("""COMPUTED_VALUE"""),129066.0) -> 129066 | D15: =IFERROR(__xludf.DUMMYFUNCTION("""COMPUTED_VALUE"""),2634.0) -> 2634 | E15: =IFERROR(__xludf.DUMMYFUNCTION("""COMPUTED_VALUE"""),0.02) -> 0.02 | F15: =IFERROR(__xludf.DUMMYFUNCTION("""COMPUTED_VALUE"""),21296.0) -> 21296 | G15: =IFERROR(__xludf.DUMMYFUNCTION("""COMPUTED_VALUE"""),21296.0) -> 21296 | H15: =IFERROR(__xludf.DUMMYFUNCTION("""COMPUTED_VALUE"""),0.0) -> 0 | I15: =IFERROR(__xludf.DUMMYFUNCTION("""COMPUTED_VALUE"""),"EXCEPTION") -> EXCEPTION | K15: =IFS(J15="Prepayment", "Update schedule, recalculate interest",J15="System Error", "Escalate to tech team",J15="Waiver Applied", "Verify approval, update ledger",J15="Partial Payment", "Contact customer for balance",J15="Rate Change", "Update loan agreement",J15="", "" ) | L15: =VLOOKUP(A15,LMS_Loan_Tape!A:Z,7,FALSE) -> Piramal | M15: =D15+H15 -> 2634 | N15: =VLOOKUP(A15,LMS_Loan_Tape!A:Z,6,FALSE) -> Home Loan | O15: =VLOOKUP(A15, LMS_Loan_Tape!A14:Z1013,11,false) -> 11
A16: =IFERROR(__xludf.DUMMYFUNCTION("""COMPUTED_VALUE"""),"LN-10048") -> LN-10048 | B16: =IFERROR(__xludf.DUMMYFUNCTION("""COMPUTED_VALUE"""),22297.0) -> 22297 | C16: =IFERROR(__xludf.DUMMYFUNCTION("""COMPUTED_VALUE"""),22297.0) -> 22297 | D16: =IFERROR(__xludf.DUMMYFUNCTION("""COMPUTED_VALUE"""),0.0) -> 0 | E16: =IFERROR(__xludf.DUMMYFUNCTION("""COMPUTED_VALUE"""),0.0) -> 0 | F16: =IFERROR(__xludf.DUMMYFUNCTION("""COMPUTED_VALUE"""),2929.0) -> 2929 | G16: =IFERROR(__xludf.DUMMYFUNCTION("""COMPUTED_VALUE"""),2899.0) -> 2899 | H16: =IFERROR(__xludf.DUMMYFUNCTION("""COMPUTED_VALUE"""),30.0) -> 30 | I16: =IFERROR(__xludf.DUMMYFUNCTION("""COMPUTED_VALUE"""),"EXCEPTION") -> EXCEPTION | K16: =IFS(J16="Prepayment", "Update schedule, recalculate interest",J16="System Error", "Escalate to tech team",J16="Waiver Applied", "Verify approval, update ledger",J16="Partial Payment", "Contact customer for balance",J16="Rate Change", "Update loan agreement",J16="", "" ) | L16: =VLOOKUP(A16,LMS_Loan_Tape!A:Z,7,FALSE) -> DMI | M16: =D16+H16 -> 30 | N16: =VLOOKUP(A16,LMS_Loan_Tape!A:Z,6,FALSE) -> Personal Loan | O16: =VLOOKUP(A16, LMS_Loan_Tape!A15:Z1014,11,false) -> 6
A17: =IFERROR(__xludf.DUMMYFUNCTION("""COMPUTED_VALUE"""),"LN-10051") -> LN-10051 | B17: =IFERROR(__xludf.DUMMYFUNCTION("""COMPUTED_VALUE"""),82659.0) -> 82659 | C17: =IFERROR(__xludf.DUMMYFUNCTION("""COMPUTED_VALUE"""),82659.0) -> 82659 | D17: =IFERROR(__xludf.DUMMYFUNCTION("""COMPUTED_VALUE"""),0.0) -> 0 | E17: =IFERROR(__xludf.DUMMYFUNCTION("""COMPUTED_VALUE"""),0.0) -> 0 | F17: =IFERROR(__xludf.DUMMYFUNCTION("""COMPUTED_VALUE"""),9574.0) -> 9574 | G17: =IFERROR(__xludf.DUMMYFUNCTION("""COMPUTED_VALUE"""),9478.0) -> 9478 | H17: =IFERROR(__xludf.DUMMYFUNCTION("""COMPUTED_VALUE"""),96.0) -> 96 | I17: =IFERROR(__xludf.DUMMYFUNCTION("""COMPUTED_VALUE"""),"EXCEPTION") -> EXCEPTION | K17: =IFS(J17="Prepayment", "Update schedule, recalculate interest",J17="System Error", "Escalate to tech team",J17="Waiver Applied", "Verify approval, update ledger",J17="Partial Payment", "Contact customer for balance",J17="Rate Change", "Update loan agreement",J17="", "" ) | L17: =VLOOKUP(A17,LMS_Loan_Tape!A:Z,7,FALSE) -> Northern Arc | M17: =D17+H17 -> 96 | N17: =VLOOKUP(A17,LMS_Loan_Tape!A:Z,6,FALSE) -> Home Loan | O17: =VLOOKUP(A17, LMS_Loan_Tape!A16:Z1015,11,false) -> 8
A18: =IFERROR(__xludf.DUMMYFUNCTION("""COMPUTED_VALUE"""),"LN-10056") -> LN-10056 | B18: =IFERROR(__xludf.DUMMYFUNCTION("""COMPUTED_VALUE"""),58280.0) -> 58280 | C18: =IFERROR(__xludf.DUMMYFUNCTION("""COMPUTED_VALUE"""),58280.0) -> 58280 | D18: =IFERROR(__xludf.DUMMYFUNCTION("""COMPUTED_VALUE"""),0.0) -> 0 | E18: =IFERROR(__xludf.DUMMYFUNCTION("""COMPUTED_VALUE"""),0.0) -> 0 | F18: =IFERROR(__xludf.DUMMYFUNCTION("""COMPUTED_VALUE"""),10932.0) -> 10932 | G18: =IFERROR(__xludf.DUMMYFUNCTION("""COMPUTED_VALUE"""),10822.0) -> 10822 | H18: =IFERROR(__xludf.DUMMYFUNCTION("""COMPUTED_VALUE"""),110.0) -> 110 | I18: =IFERROR(__xludf.DUMMYFUNCTION("""COMPUTED_VALUE"""),"EXCEPTION") -> EXCEPTION | K18: =IFS(J18="Prepayment", "Update schedule, recalculate interest",J18="System Error", "Escalate to tech team",J18="Waiver Applied", "Verify approval, update ledger",J18="Partial Payment", "Contact customer for balance",J18="Rate Change", "Update loan agreement",J18="", "" ) | L18: =VLOOKUP(A18,LMS_Loan_Tape!A:Z,7,FALSE) -> Liquiloans | M18: =D18+H18 -> 110 | N18: =VLOOKUP(A18,LMS_Loan_Tape!A:Z,6,FALSE) -> Gold Loan | O18: =VLOOKUP(A18, LMS_Loan_Tape!A17:Z1016,11,false) -> 10
A19: =IFERROR(__xludf.DUMMYFUNCTION("""COMPUTED_VALUE"""),"LN-10062") -> LN-10062 | B19: =IFERROR(__xludf.DUMMYFUNCTION("""COMPUTED_VALUE"""),362648.0) -> 362648 | C19: =IFERROR(__xludf.DUMMYFUNCTION("""COMPUTED_VALUE"""),355395.0) -> 355395 | D19: =IFERROR(__xludf.DUMMYFUNCTION("""COMPUTED_VALUE"""),7253.0) -> 7253 | E19: =IFERROR(__xludf.DUMMYFUNCTION("""COMPUTED_VALUE"""),0.020000110299794843) -> 0.02000011 | F19: =IFERROR(__xludf.DUMMYFUNCTION("""COMPUTED_VALUE"""),43577.0) -> 43577 | G19: =IFERROR(__xludf.DUMMYFUNCTION("""COMPUTED_VALUE"""),43577.0) -> 43577 | H19: =IFERROR(__xludf.DUMMYFUNCTION("""COMPUTED_VALUE"""),0.0) -> 0 | I19: =IFERROR(__xludf.DUMMYFUNCTION("""COMPUTED_VALUE"""),"EXCEPTION") -> EXCEPTION | K19: =IFS(J19="Prepayment", "Update schedule, recalculate interest",J19="System Error", "Escalate to tech team",J19="Waiver Applied", "Verify approval, update ledger",J19="Partial Payment", "Contact customer for balance",J19="Rate Change", "Update loan agreement",J19="", "" ) | L19: =VLOOKUP(A19,LMS_Loan_Tape!A:Z,7,FALSE) -> Liquiloans | M19: =D19+H19 -> 7253 | N19: =VLOOKUP(A19,LMS_Loan_Tape!A:Z,6,FALSE) -> Business Loan | O19: =VLOOKUP(A19, LMS_Loan_Tape!A18:Z1017,11,false) -> 1
A20: =IFERROR(__xludf.DUMMYFUNCTION("""COMPUTED_VALUE"""),"LN-10069") -> LN-10069 | B20: =IFERROR(__xludf.DUMMYFUNCTION("""COMPUTED_VALUE"""),109536.0) -> 109536 | C20: =IFERROR(__xludf.DUMMYFUNCTION("""COMPUTED_VALUE"""),110210.0) -> 110210 | D20: =IFERROR(__xludf.DUMMYFUNCTION("""COMPUTED_VALUE"""),-674.0) -> -674 | E20: =IFERROR(__xludf.DUMMYFUNCTION("""COMPUTED_VALUE"""),-0.006153228162430616) -> -0.0061532282 | F20: =IFERROR(__xludf.DUMMYFUNCTION("""COMPUTED_VALUE"""),25724.0) -> 25724 | G20: =IFERROR(__xludf.DUMMYFUNCTION("""COMPUTED_VALUE"""),25724.0) -> 25724 | H20: =IFERROR(__xludf.DUMMYFUNCTION("""COMPUTED_VALUE"""),0.0) -> 0 | I20: =IFERROR(__xludf.DUMMYFUNCTION("""COMPUTED_VALUE"""),"EXCEPTION") -> EXCEPTION | J20: =IFERROR(__xludf.DUMMYFUNCTION("""COMPUTED_VALUE"""),"System Error") -> System Error | K20: =IFS(J20="Prepayment", "Update schedule, recalculate interest",J20="System Error", "Escalate to tech team",J20="Waiver Applied", "Verify approval, update ledger",J20="Partial Payment", "Contact customer for balance",J20="Rate Change", "Update loan agreement",J20="", "" ) -> Escalate to tech team | L20: =VLOOKUP(A20,LMS_Loan_Tape!A:Z,7,FALSE) -> DMI | M20: =D20+H20 -> -674 | N20: =VLOOKUP(A20,LMS_Loan_Tape!A:Z,6,FALSE) -> Home Loan | O20: =VLOOKUP(A20, LMS_Loan_Tape!A19:Z1018,11,false) -> 7
A21: =IFERROR(__xludf.DUMMYFUNCTION("""COMPUTED_VALUE"""),"LN-10075") -> LN-10075 | B21: =IFERROR(__xludf.DUMMYFUNCTION("""COMPUTED_VALUE"""),88094.0) -> 88094 | C21: =IFERROR(__xludf.DUMMYFUNCTION("""COMPUTED_VALUE"""),92498.0) -> 92498 | D21: =IFERROR(__xludf.DUMMYFUNCTION("""COMPUTED_VALUE"""),-4404.0) -> -4404 | E21: =IFERROR(__xludf.DUMMYFUNCTION("""COMPUTED_VALUE"""),-0.04999205394237973) -> -0.049992054 | F21: =IFERROR(__xludf.DUMMYFUNCTION("""COMPUTED_VALUE"""),24407.0) -> 24407 | G21: =IFERROR(__xludf.DUMMYFUNCTION("""COMPUTED_VALUE"""),24407.0) -> 24407 | H21: =IFERROR(__xludf.DUMMYFUNCTION("""COMPUTED_VALUE"""),0.0) -> 0 | I21: =IFERROR(__xludf.DUMMYFUNCTION("""COMPUTED_VALUE"""),"EXCEPTION") -> EXCEPTION | J21: =IFERROR(__xludf.DUMMYFUNCTION("""COMPUTED_VALUE"""),"Rate Change") -> Rate Change | K21: =IFS(J21="Prepayment", "Update schedule, recalculate interest",J21="System Error", "Escalate to tech team",J21="Waiver Applied", "Verify approval, update ledger",J21="Partial Payment", "Contact customer for balance",J21="Rate Change", "Update loan agreement",J21="", "" ) -> Update loan agreement | L21: =VLOOKUP(A21,LMS_Loan_Tape!A:Z,7,FALSE) -> Tata Capital | M21: =D21+H21 -> -4404 | N21: =VLOOKUP(A21,LMS_Loan_Tape!A:Z,6,FALSE) -> Gold Loan | O21: =VLOOKUP(A21, LMS_Loan_Tape!A20:Z1019,11,false) -> 10
A22: =IFERROR(__xludf.DUMMYFUNCTION("""COMPUTED_VALUE"""),"LN-10076") -> LN-10076 | B22: =IFERROR(__xludf.DUMMYFUNCTION("""COMPUTED_VALUE"""),41646.0) -> 41646 | C22: =IFERROR(__xludf.DUMMYFUNCTION("""COMPUTED_VALUE"""),43728.0) -> 43728 | D22: =IFERROR(__xludf.DUMMYFUNCTION("""COMPUTED_VALUE"""),-2082.0) -> -2082 | E22: =IFERROR(__xludf.DUMMYFUNCTION("""COMPUTED_VALUE"""),-0.04999279642702781) -> -0.049992796 | F22: =IFERROR(__xludf.DUMMYFUNCTION("""COMPUTED_VALUE"""),29276.0) -> 29276 | G22: =IFERROR(__xludf.DUMMYFUNCTION("""COMPUTED_VALUE"""),29276.0) -> 29276 | H22: =IFERROR(__xludf.DUMMYFUNCTION("""COMPUTED_VALUE"""),0.0) -> 0 | I22: =IFERROR(__xludf.DUMMYFUNCTION("""COMPUTED_VALUE"""),"EXCEPTION") -> EXCEPTION | J22: =IFERROR(__xludf.DUMMYFUNCTION("""COMPUTED_VALUE"""),"Rate Change") -> Rate Change | K22: =IFS(J22="Prepayment", "Update schedule, recalculate interest",J22="System Error", "Escalate to tech team",J22="Waiver Applied", "Verify approval, update ledger",J22="Partial Payment", "Contact customer for balance",J22="Rate Change", "Update loan agreement",J22="", "" ) -> Update loan agreement | L22: =VLOOKUP(A22,LMS_Loan_Tape!A:Z,7,FALSE) -> Tata Capital | M22: =D22+H22 -> -2082 | N22: =VLOOKUP(A22,LMS_Loan_Tape!A:Z,6,FALSE) -> Home Loan | O22: =VLOOKUP(A22, LMS_Loan_Tape!A21:Z1020,11,false) -> 2
A23: =IFERROR(__xludf.DUMMYFUNCTION("""COMPUTED_VALUE"""),"LN-10081") -> LN-10081 | B23: =IFERROR(__xludf.DUMMYFUNCTION("""COMPUTED_VALUE"""),291821.0) -> 291821 | C23: =IFERROR(__xludf.DUMMYFUNCTION("""COMPUTED_VALUE"""),291821.0) -> 291821 | D23: =IFERROR(__xludf.DUMMYFUNCTION("""COMPUTED_VALUE"""),0.0) -> 0 | E23: =IFERROR(__xludf.DUMMYFUNCTION("""COMPUTED_VALUE"""),0.0) -> 0 | F23: =IFERROR(__xludf.DUMMYFUNCTION("""COMPUTED_VALUE"""),36865.0) -> 36865 | G23: =IFERROR(__xludf.DUMMYFUNCTION("""COMPUTED_VALUE"""),36496.0) -> 36496 | H23: =IFERROR(__xludf.DUMMYFUNCTION("""COMPUTED_VALUE"""),369.0) -> 369 | I23: =IFERROR(__xludf.DUMMYFUNCTION("""COMPUTED_VALUE"""),"EXCEPTION") -> EXCEPTION | K23: =IFS(J23="Prepayment", "Update schedule, recalculate interest",J23="System Error", "Escalate to tech team",J23="Waiver Applied", "Verify approval, update ledger",J23="Partial Payment", "Contact customer for balance",J23="Rate Change", "Update loan agreement",J23="", "" ) | L23: =VLOOKUP(A23,LMS_Loan_Tape!A:Z,7,FALSE) -> Piramal | M23: =D23+H23 -> 369 | N23: =VLOOKUP(A23,LMS_Loan_Tape!A:Z,6,FALSE) -> Personal Loan | O23: =VLOOKUP(A23, LMS_Loan_Tape!A22:Z1021,11,false) -> 7
A24: =IFERROR(__xludf.DUMMYFUNCTION("""COMPUTED_VALUE"""),"LN-10082") -> LN-10082 | B24: =IFERROR(__xludf.DUMMYFUNCTION("""COMPUTED_VALUE"""),296219.0) -> 296219 | C24: =IFERROR(__xludf.DUMMYFUNCTION("""COMPUTED_VALUE"""),290294.0) -> 290294 | D24: =IFERROR(__xludf.DUMMYFUNCTION("""COMPUTED_VALUE"""),5925.0) -> 5925 | E24: =IFERROR(__xludf.DUMMYFUNCTION("""COMPUTED_VALUE"""),0.02000209304602338) -> 0.020002093 | F24: =IFERROR(__xludf.DUMMYFUNCTION("""COMPUTED_VALUE"""),32049.0) -> 32049 | G24: =IFERROR(__xludf.DUMMYFUNCTION("""COMPUTED_VALUE"""),32049.0) -> 32049 | H24: =IFERROR(__xludf.DUMMYFUNCTION("""COMPUTED_VALUE"""),0.0) -> 0 | I24: =IFERROR(__xludf.DUMMYFUNCTION("""COMPUTED_VALUE"""),"EXCEPTION") -> EXCEPTION | K24: =IFS(J24="Prepayment", "Update schedule, recalculate interest",J24="System Error", "Escalate to tech team",J24="Waiver Applied", "Verify approval, update ledger",J24="Partial Payment", "Contact customer for balance",J24="Rate Change", "Update loan agreement",J24="", "" ) | L24: =VLOOKUP(A24,LMS_Loan_Tape!A:Z,7,FALSE) -> Northern Arc | M24: =D24+H24 -> 5925 | N24: =VLOOKUP(A24,LMS_Loan_Tape!A:Z,6,FALSE) -> Gold Loan | O24: =VLOOKUP(A24, LMS_Loan_Tape!A23:Z1022,11,false) -> 7
A25: =IFERROR(__xludf.DUMMYFUNCTION("""COMPUTED_VALUE"""),"LN-10085") -> LN-10085 | B25: =IFERROR(__xludf.DUMMYFUNCTION("""COMPUTED_VALUE"""),112602.0) -> 112602 | C25: =IFERROR(__xludf.DUMMYFUNCTION("""COMPUTED_VALUE"""),67561.0) -> 67561 | D25: =IFERROR(__xludf.DUMMYFUNCTION("""COMPUTED_VALUE"""),45041.0) -> 45041 | E25: =IFERROR(__xludf.DUMMYFUNCTION("""COMPUTED_VALUE"""),0.400001776167386) -> 0.40000178 | F25: =IFERROR(__xludf.DUMMYFUNCTION("""COMPUTED_VALUE"""),13350.0) -> 13350 | G25: =IFERROR(__xludf.DUMMYFUNCTION("""COMPUTED_VALUE"""),13350.0) -> 13350 | H25: =IFERROR(__xludf.DUMMYFUNCTION("""COMPUTED_VALUE"""),0.0) -> 0 | I25: =IFERROR(__xludf.DUMMYFUNCTION("""COMPUTED_VALUE"""),"EXCEPTION") -> EXCEPTION | J25: =IFERROR(__xludf.DUMMYFUNCTION("""COMPUTED_VALUE"""),"Partial Payment") -> Partial Payment | K25: =IFS(J25="Prepayment", "Update schedule, recalculate interest",J25="System Error", "Escalate to tech team",J25="Waiver Applied", "Verify approval, update ledger",J25="Partial Payment", "Contact customer for balance",J25="Rate Change", "Update loan agreement",J25="", "" ) -> Contact customer for balance | L25: =VLOOKUP(A25,LMS_Loan_Tape!A:Z,7,FALSE) -> Piramal | M25: =D25+H25 -> 45041 | N25: =VLOOKUP(A25,LMS_Loan_Tape!A:Z,6,FALSE) -> Business Loan | O25: =VLOOKUP(A25, LMS_Loan_Tape!A24:Z1023,11,false) -> 9
A26: =IFERROR(__xludf.DUMMYFUNCTION("""COMPUTED_VALUE"""),"LN-10087") -> LN-10087 | B26: =IFERROR(__xludf.DUMMYFUNCTION("""COMPUTED_VALUE"""),53344.0) -> 53344 | C26: =IFERROR(__xludf.DUMMYFUNCTION("""COMPUTED_VALUE"""),32006.0) -> 32006 | D26: =IFERROR(__xludf.DUMMYFUNCTION("""COMPUTED_VALUE"""),21338.0) -> 21338 | E26: =IFERROR(__xludf.DUMMYFUNCTION("""COMPUTED_VALUE"""),0.40000749850029993) -> 0.4000075 | F26: =IFERROR(__xludf.DUMMYFUNCTION("""COMPUTED_VALUE"""),10168.0) -> 10168 | G26: =IFERROR(__xludf.DUMMYFUNCTION("""COMPUTED_VALUE"""),10168.0) -> 10168 | H26: =IFERROR(__xludf.DUMMYFUNCTION("""COMPUTED_VALUE"""),0.0) -> 0 | I26: =IFERROR(__xludf.DUMMYFUNCTION("""COMPUTED_VALUE"""),"EXCEPTION") -> EXCEPTION | J26: =IFERROR(__xludf.DUMMYFUNCTION("""COMPUTED_VALUE"""),"Partial Payment") -> Partial Payment | K26: =IFS(J26="Prepayment", "Update schedule, recalculate interest",J26="System Error", "Escalate to tech team",J26="Waiver Applied", "Verify approval, update ledger",J26="Partial Payment", "Contact customer for balance",J26="Rate Change", "Update loan agreement",J26="", "" ) -> Contact customer for balance | L26: =VLOOKUP(A26,LMS_Loan_Tape!A:Z,7,FALSE) -> Northern Arc | M26: =D26+H26 -> 21338 | N26: =VLOOKUP(A26,LMS_Loan_Tape!A:Z,6,FALSE) -> Gold Loan | O26: =VLOOKUP(A26, LMS_Loan_Tape!A25:Z1024,11,false) -> 9
A27: =IFERROR(__xludf.DUMMYFUNCTION("""COMPUTED_VALUE"""),"LN-10091") -> LN-10091 | B27: =IFERROR(__xludf.DUMMYFUNCTION("""COMPUTED_VALUE"""),30963.0) -> 30963 | C27: =IFERROR(__xludf.DUMMYFUNCTION("""COMPUTED_VALUE"""),30343.0) -> 30343 | D27: =IFERROR(__xludf.DUMMYFUNCTION("""COMPUTED_VALUE"""),620.0) -> 620 | E27: =IFERROR(__xludf.DUMMYFUNCTION("""COMPUTED_VALUE"""),0.02002389949294319) -> 0.020023899 | F27: =IFERROR(__xludf.DUMMYFUNCTION("""COMPUTED_VALUE"""),23097.0) -> 23097 | G27: =IFERROR(__xludf.DUMMYFUNCTION("""COMPUTED_VALUE"""),23097.0) -> 23097 | H27: =IFERROR(__xludf.DUMMYFUNCTION("""COMPUTED_VALUE"""),0.0) -> 0 | I27: =IFERROR(__xludf.DUMMYFUNCTION("""COMPUTED_VALUE"""),"EXCEPTION") -> EXCEPTION | K27: =IFS(J27="Prepayment", "Update schedule, recalculate interest",J27="System Error", "Escalate to tech team",J27="Waiver Applied", "Verify approval, update ledger",J27="Partial Payment", "Contact customer for balance",J27="Rate Change", "Update loan agreement",J27="", "" ) | L27: =VLOOKUP(A27,LMS_Loan_Tape!A:Z,7,FALSE) -> DMI | M27: =D27+H27 -> 620 | N27: =VLOOKUP(A27,LMS_Loan_Tape!A:Z,6,FALSE) -> Home Loan | O27: =VLOOKUP(A27, LMS_Loan_Tape!A26:Z1025,11,false) -> 3
A28: =IFERROR(__xludf.DUMMYFUNCTION("""COMPUTED_VALUE"""),"LN-10093") -> LN-10093 | B28: =IFERROR(__xludf.DUMMYFUNCTION("""COMPUTED_VALUE"""),43894.0) -> 43894 | C28: =IFERROR(__xludf.DUMMYFUNCTION("""COMPUTED_VALUE"""),35115.0) -> 35115 | D28: =IFERROR(__xludf.DUMMYFUNCTION("""COMPUTED_VALUE"""),8779.0) -> 8779 | E28: =IFERROR(__xludf.DUMMYFUNCTION("""COMPUTED_VALUE"""),0.2000045564314029) -> 0.20000456 | F28: =IFERROR(__xludf.DUMMYFUNCTION("""COMPUTED_VALUE"""),53579.0) -> 53579 | G28: =IFERROR(__xludf.DUMMYFUNCTION("""COMPUTED_VALUE"""),53579.0) -> 53579 | H28: =IFERROR(__xludf.DUMMYFUNCTION("""COMPUTED_VALUE"""),0.0) -> 0 | I28: =IFERROR(__xludf.DUMMYFUNCTION("""COMPUTED_VALUE"""),"EXCEPTION") -> EXCEPTION | J28: =IFERROR(__xludf.DUMMYFUNCTION("""COMPUTED_VALUE"""),"Prepayment") -> Prepayment | K28: =IFS(J28="Prepayment", "Update schedule, recalculate interest",J28="System Error", "Escalate to tech team",J28="Waiver Applied", "Verify approval, update ledger",J28="Partial Payment", "Contact customer for balance",J28="Rate Change", "Update loan agreement",J28="", "" ) -> Update schedule, recalculate interest | L28: =VLOOKUP(A28,LMS_Loan_Tape!A:Z,7,FALSE) -> Tata Capital | M28: =D28+H28 -> 8779 | N28: =VLOOKUP(A28,LMS_Loan_Tape!A:Z,6,FALSE) -> Gold Loan | O28: =VLOOKUP(A28, LMS_Loan_Tape!A27:Z1026,11,false) -> 3
A29: =IFERROR(__xludf.DUMMYFUNCTION("""COMPUTED_VALUE"""),"LN-10097") -> LN-10097 | B29: =IFERROR(__xludf.DUMMYFUNCTION("""COMPUTED_VALUE"""),286683.0) -> 286683 | C29: =IFERROR(__xludf.DUMMYFUNCTION("""COMPUTED_VALUE"""),286683.0) -> 286683 | D29: =IFERROR(__xludf.DUMMYFUNCTION("""COMPUTED_VALUE"""),0.0) -> 0 | E29: =IFERROR(__xludf.DUMMYFUNCTION("""COMPUTED_VALUE"""),0.0) -> 0 | F29: =IFERROR(__xludf.DUMMYFUNCTION("""COMPUTED_VALUE"""),45617.0) -> 45617 | G29: =IFERROR(__xludf.DUMMYFUNCTION("""COMPUTED_VALUE"""),45160.0) -> 45160 | H29: =IFERROR(__xludf.DUMMYFUNCTION("""COMPUTED_VALUE"""),457.0) -> 457 | I29: =IFERROR(__xludf.DUMMYFUNCTION("""COMPUTED_VALUE"""),"EXCEPTION") -> EXCEPTION | K29: =IFS(J29="Prepayment", "Update schedule, recalculate interest",J29="System Error", "Escalate to tech team",J29="Waiver Applied", "Verify approval, update ledger",J29="Partial Payment", "Contact customer for balance",J29="Rate Change", "Update loan agreement",J29="", "" ) | L29: =VLOOKUP(A29,LMS_Loan_Tape!A:Z,7,FALSE) -> Liquiloans | M29: =D29+H29 -> 457 | N29: =VLOOKUP(A29,LMS_Loan_Tape!A:Z,6,FALSE) -> Home Loan | O29: =VLOOKUP(A29, LMS_Loan_Tape!A28:Z1027,11,false) -> 8
A30: =IFERROR(__xludf.DUMMYFUNCTION("""COMPUTED_VALUE"""),"LN-10098") -> LN-10098 | B30: =IFERROR(__xludf.DUMMYFUNCTION("""COMPUTED_VALUE"""),188079.0) -> 188079 | C30: =IFERROR(__xludf.DUMMYFUNCTION("""COMPUTED_VALUE"""),188079.0) -> 188079 | D30: =IFERROR(__xludf.DUMMYFUNCTION("""COMPUTED_VALUE"""),0.0) -> 0 | E30: =IFERROR(__xludf.DUMMYFUNCTION("""COMPUTED_VALUE"""),0.0) -> 0 | F30: =IFERROR(__xludf.DUMMYFUNCTION("""COMPUTED_VALUE"""),18362.0) -> 18362 | G30: =IFERROR(__xludf.DUMMYFUNCTION("""COMPUTED_VALUE"""),18178.0) -> 18178 | H30: =IFERROR(__xludf.DUMMYFUNCTION("""COMPUTED_VALUE"""),184.0) -> 184 | I30: =IFERROR(__xludf.DUMMYFUNCTION("""COMPUTED_VALUE"""),"EXCEPTION") -> EXCEPTION | K30: =IFS(J30="Prepayment", "Update schedule, recalculate interest",J30="System Error", "Escalate to tech team",J30="Waiver Applied", "Verify approval, update ledger",J30="Partial Payment", "Contact customer for balance",J30="Rate Change", "Update loan agreement",J30="", "" ) | L30: =VLOOKUP(A30,LMS_Loan_Tape!A:Z,7,FALSE) -> Liquiloans | M30: =D30+H30 -> 184 | N30: =VLOOKUP(A30,LMS_Loan_Tape!A:Z,6,FALSE) -> Home Loan | O30: =VLOOKUP(A30, LMS_Loan_Tape!A29:Z1028,11,false) -> 6
A31: =IFERROR(__xludf.DUMMYFUNCTION("""COMPUTED_VALUE"""),"LN-10102") -> LN-10102 | B31: =IFERROR(__xludf.DUMMYFUNCTION("""COMPUTED_VALUE"""),333909.0) -> 333909 | C31: =IFERROR(__xludf.DUMMYFUNCTION("""COMPUTED_VALUE"""),300518.0) -> 300518 | D31: =IFERROR(__xludf.DUMMYFUNCTION("""COMPUTED_VALUE"""),33391.0) -> 33391 | E31: =IFERROR(__xludf.DUMMYFUNCTION("""COMPUTED_VALUE"""),0.10000029948279322) -> 0.1000003 | F31: =IFERROR(__xludf.DUMMYFUNCTION("""COMPUTED_VALUE"""),41478.0) -> 41478 | G31: =IFERROR(__xludf.DUMMYFUNCTION("""COMPUTED_VALUE"""),20739.0) -> 20739 | H31: =IFERROR(__xludf.DUMMYFUNCTION("""COMPUTED_VALUE"""),20739.0) -> 20739 | I31: =IFERROR(__xludf.DUMMYFUNCTION("""COMPUTED_VALUE"""),"EXCEPTION") -> EXCEPTION | J31: =IFERROR(__xludf.DUMMYFUNCTION("""COMPUTED_VALUE"""),"Waiver Applied") -> Waiver Applied | K31: =IFS(J31="Prepayment", "Update schedule, recalculate interest",J31="System Error", "Escalate to tech team",J31="Waiver Applied", "Verify approval, update ledger",J31="Partial Payment", "Contact customer for balance",J31="Rate Change", "Update loan agreement",J31="", "" ) -> Verify approval, update ledger | L31: =VLOOKUP(A31,LMS_Loan_Tape!A:Z,7,FALSE) -> DMI | M31: =D31+H31 -> 54130 | N31: =VLOOKUP(A31,LMS_Loan_Tape!A:Z,6,FALSE) -> Home Loan | O31: =VLOOKUP(A31, LMS_Loan_Tape!A30:Z1029,11,false) -> 8
A32: =IFERROR(__xludf.DUMMYFUNCTION("""COMPUTED_VALUE"""),"LN-10105") -> LN-10105 | B32: =IFERROR(__xludf.DUMMYFUNCTION("""COMPUTED_VALUE"""),78377.0) -> 78377 | C32: =IFERROR(__xludf.DUMMYFUNCTION("""COMPUTED_VALUE"""),70539.0) -> 70539 | D32: =IFERROR(__xludf.DUMMYFUNCTION("""COMPUTED_VALUE"""),7838.0) -> 7838 | E32: =IFERROR(__xludf.DUMMYFUNCTION("""COMPUTED_VALUE"""),0.1000038276535208) -> 0.10000383 | F32: =IFERROR(__xludf.DUMMYFUNCTION("""COMPUTED_VALUE"""),20750.0) -> 20750 | G32: =IFERROR(__xludf.DUMMYFUNCTION("""COMPUTED_VALUE"""),10375.0) -> 10375 | H32: =IFERROR(__xludf.DUMMYFUNCTION("""COMPUTED_VALUE"""),10375.0) -> 10375 | I32: =IFERROR(__xludf.DUMMYFUNCTION("""COMPUTED_VALUE"""),"EXCEPTION") -> EXCEPTION | J32: =IFERROR(__xludf.DUMMYFUNCTION("""COMPUTED_VALUE"""),"Waiver Applied") -> Waiver Applied | K32: =IFS(J32="Prepayment", "Update schedule, recalculate interest",J32="System Error", "Escalate to tech team",J32="Waiver Applied", "Verify approval, update ledger",J32="Partial Payment", "Contact customer for balance",J32="Rate Change", "Update loan agreement",J32="", "" ) -> Verify approval, update ledger | L32: =VLOOKUP(A32,LMS_Loan_Tape!A:Z,7,FALSE) -> Liquiloans | M32: =D32+H32 -> 18213 | N32: =VLOOKUP(A32,LMS_Loan_Tape!A:Z,6,FALSE) -> Gold Loan | O32: =VLOOKUP(A32, LMS_Loan_Tape!A31:Z1030,11,false) -> 8
A33: =IFERROR(__xludf.DUMMYFUNCTION("""COMPUTED_VALUE"""),"LN-10110") -> LN-10110 | B33: =IFERROR(__xludf.DUMMYFUNCTION("""COMPUTED_VALUE"""),105195.0) -> 105195 | C33: =IFERROR(__xludf.DUMMYFUNCTION("""COMPUTED_VALUE"""),105791.0) -> 105791 | D33: =IFERROR(__xludf.DUMMYFUNCTION("""COMPUTED_VALUE"""),-596.0) -> -596 | E33: =IFERROR(__xludf.DUMMYFUNCTION("""COMPUTED_VALUE"""),-0.0056656685203669375) -> -0.0056656685 | F33: =IFERROR(__xludf.DUMMYFUNCTION("""COMPUTED_VALUE"""),31570.0) -> 31570 | G33: =IFERROR(__xludf.DUMMYFUNCTION("""COMPUTED_VALUE"""),31570.0) -> 31570 | H33: =IFERROR(__xludf.DUMMYFUNCTION("""COMPUTED_VALUE"""),0.0) -> 0 | I33: =IFERROR(__xludf.DUMMYFUNCTION("""COMPUTED_VALUE"""),"EXCEPTION") -> EXCEPTION | J33: =IFERROR(__xludf.DUMMYFUNCTION("""COMPUTED_VALUE"""),"System Error") -> System Error | K33: =IFS(J33="Prepayment", "Update schedule, recalculate interest",J33="System Error", "Escalate to tech team",J33="Waiver Applied", "Verify approval, update ledger",J33="Partial Payment", "Contact customer for balance",J33="Rate Change", "Update loan agreement",J33="", "" ) -> Escalate to tech team | L33: =VLOOKUP(A33,LMS_Loan_Tape!A:Z,7,FALSE) -> Tata Capital | M33: =D33+H33 -> -596 | N33: =VLOOKUP(A33,LMS_Loan_Tape!A:Z,6,FALSE) -> Home Loan | O33: =VLOOKUP(A33, LMS_Loan_Tape!A32:Z1031,11,false) -> 12
A34: =IFERROR(__xludf.DUMMYFUNCTION("""COMPUTED_VALUE"""),"LN-10118") -> LN-10118 | B34: =IFERROR(__xludf.DUMMYFUNCTION("""COMPUTED_VALUE"""),11813.0) -> 11813 | C34: =IFERROR(__xludf.DUMMYFUNCTION("""COMPUTED_VALUE"""),10631.0) -> 10631 | D34: =IFERROR(__xludf.DUMMYFUNCTION("""COMPUTED_VALUE"""),1182.0) -> 1182 | E34: =IFERROR(__xludf.DUMMYFUNCTION("""COMPUTED_VALUE"""),0.100059256751037) -> 0.10005926 | F34: =IFERROR(__xludf.DUMMYFUNCTION("""COMPUTED_VALUE"""),12323.0) -> 12323 | G34: =IFERROR(__xludf.DUMMYFUNCTION("""COMPUTED_VALUE"""),6161.0) -> 6161 | H34: =IFERROR(__xludf.DUMMYFUNCTION("""COMPUTED_VALUE"""),6162.0) -> 6162 | I34: =IFERROR(__xludf.DUMMYFUNCTION("""COMPUTED_VALUE"""),"EXCEPTION") -> EXCEPTION | J34: =IFERROR(__xludf.DUMMYFUNCTION("""COMPUTED_VALUE"""),"Waiver Applied") -> Waiver Applied | K34: =IFS(J34="Prepayment", "Update schedule, recalculate interest",J34="System Error", "Escalate to tech team",J34="Waiver Applied", "Verify approval, update ledger",J34="Partial Payment", "Contact customer for balance",J34="Rate Change", "Update loan agreement",J34="", "" ) -> Verify approval, update ledger | L34: =VLOOKUP(A34,LMS_Loan_Tape!A:Z,7,FALSE) -> Tata Capital | M34: =D34+H34 -> 7344 | N34: =VLOOKUP(A34,LMS_Loan_Tape!A:Z,6,FALSE) -> Business Loan | O34: =VLOOKUP(A34, LMS_Loan_Tape!A33:Z1032,11,false) -> 4
A35: =IFERROR(__xludf.DUMMYFUNCTION("""COMPUTED_VALUE"""),"LN-10125") -> LN-10125 | B35: =IFERROR(__xludf.DUMMYFUNCTION("""COMPUTED_VALUE"""),396217.0) -> 396217 | C35: =IFERROR(__xludf.DUMMYFUNCTION("""COMPUTED_VALUE"""),396217.0) -> 396217 | D35: =IFERROR(__xludf.DUMMYFUNCTION("""COMPUTED_VALUE"""),0.0) -> 0 | E35: =IFERROR(__xludf.DUMMYFUNCTION("""COMPUTED_VALUE"""),0.0) -> 0 | F35: =IFERROR(__xludf.DUMMYFUNCTION("""COMPUTED_VALUE"""),27455.0) -> 27455 | G35: =IFERROR(__xludf.DUMMYFUNCTION("""COMPUTED_VALUE"""),27180.0) -> 27180 | H35: =IFERROR(__xludf.DUMMYFUNCTION("""COMPUTED_VALUE"""),275.0) -> 275 | I35: =IFERROR(__xludf.DUMMYFUNCTION("""COMPUTED_VALUE"""),"EXCEPTION") -> EXCEPTION | K35: =IFS(J35="Prepayment", "Update schedule, recalculate interest",J35="System Error", "Escalate to tech team",J35="Waiver Applied", "Verify approval, update ledger",J35="Partial Payment", "Contact customer for balance",J35="Rate Change", "Update loan agreement",J35="", "" ) | L35: =VLOOKUP(A35,LMS_Loan_Tape!A:Z,7,FALSE) -> Tata Capital | M35: =D35+H35 -> 275 | N35: =VLOOKUP(A35,LMS_Loan_Tape!A:Z,6,FALSE) -> Personal Loan | O35: =VLOOKUP(A35, LMS_Loan_Tape!A34:Z1033,11,false) -> 1
A36: =IFERROR(__xludf.DUMMYFUNCTION("""COMPUTED_VALUE"""),"LN-10127") -> LN-10127 | B36: =IFERROR(__xludf.DUMMYFUNCTION("""COMPUTED_VALUE"""),140015.0) -> 140015 | C36: =IFERROR(__xludf.DUMMYFUNCTION("""COMPUTED_VALUE"""),137214.0) -> 137214 | D36: =IFERROR(__xludf.DUMMYFUNCTION("""COMPUTED_VALUE"""),2801.0) -> 2801 | E36: =IFERROR(__xludf.DUMMYFUNCTION("""COMPUTED_VALUE"""),0.020004999464343105) -> 0.020004999 | F36: =IFERROR(__xludf.DUMMYFUNCTION("""COMPUTED_VALUE"""),17164.0) -> 17164 | G36: =IFERROR(__xludf.DUMMYFUNCTION("""COMPUTED_VALUE"""),17164.0) -> 17164 | H36: =IFERROR(__xludf.DUMMYFUNCTION("""COMPUTED_VALUE"""),0.0) -> 0 | I36: =IFERROR(__xludf.DUMMYFUNCTION("""COMPUTED_VALUE"""),"EXCEPTION") -> EXCEPTION | K36: =IFS(J36="Prepayment", "Update schedule, recalculate interest",J36="System Error", "Escalate to tech team",J36="Waiver Applied", "Verify approval, update ledger",J36="Partial Payment", "Contact customer for balance",J36="Rate Change", "Update loan agreement",J36="", "" ) | L36: =VLOOKUP(A36,LMS_Loan_Tape!A:Z,7,FALSE) -> Piramal | M36: =D36+H36 -> 2801 | N36: =VLOOKUP(A36,LMS_Loan_Tape!A:Z,6,FALSE) -> Gold Loan | O36: =VLOOKUP(A36, LMS_Loan_Tape!A35:Z1034,11,false) -> 4
A37: =IFERROR(__xludf.DUMMYFUNCTION("""COMPUTED_VALUE"""),"LN-10131") -> LN-10131 | B37: =IFERROR(__xludf.DUMMYFUNCTION("""COMPUTED_VALUE"""),310973.0) -> 310973 | C37: =IFERROR(__xludf.DUMMYFUNCTION("""COMPUTED_VALUE"""),326521.0) -> 326521 | D37: =IFERROR(__xludf.DUMMYFUNCTION("""COMPUTED_VALUE"""),-15548.0) -> -15548 | E37: =IFERROR(__xludf.DUMMYFUNCTION("""COMPUTED_VALUE"""),-0.04999790978638017) -> -0.04999791 | F37: =IFERROR(__xludf.DUMMYFUNCTION("""COMPUTED_VALUE"""),38472.0) -> 38472 | G37: =IFERROR(__xludf.DUMMYFUNCTION("""COMPUTED_VALUE"""),38472.0) -> 38472 | H37: =IFERROR(__xludf.DUMMYFUNCTION("""COMPUTED_VALUE"""),0.0) -> 0 | I37: =IFERROR(__xludf.DUMMYFUNCTION("""COMPUTED_VALUE"""),"EXCEPTION") -> EXCEPTION | J37: =IFERROR(__xludf.DUMMYFUNCTION("""COMPUTED_VALUE"""),"Rate Change") -> Rate Change | K37: =IFS(J37="Prepayment", "Update schedule, recalculate interest",J37="System Error", "Escalate to tech team",J37="Waiver Applied", "Verify approval, update ledger",J37="Partial Payment", "Contact customer for balance",J37="Rate Change", "Update loan agreement",J37="", "" ) -> Update loan agreement | L37: =VLOOKUP(A37,LMS_Loan_Tape!A:Z,7,FALSE) -> DMI | M37: =D37+H37 -> -15548 | N37: =VLOOKUP(A37,LMS_Loan_Tape!A:Z,6,FALSE) -> Home Loan | O37: =VLOOKUP(A37, LMS_Loan_Tape!A36:Z1035,11,false) -> 8
A38: =IFERROR(__xludf.DUMMYFUNCTION("""COMPUTED_VALUE"""),"LN-10132") -> LN-10132 | B38: =IFERROR(__xludf.DUMMYFUNCTION("""COMPUTED_VALUE"""),358817.0) -> 358817 | C38: =IFERROR(__xludf.DUMMYFUNCTION("""COMPUTED_VALUE"""),358817.0) -> 358817 | D38: =IFERROR(__xludf.DUMMYFUNCTION("""COMPUTED_VALUE"""),0.0) -> 0 | E38: =IFERROR(__xludf.DUMMYFUNCTION("""COMPUTED_VALUE"""),0.0) -> 0 | F38: =IFERROR(__xludf.DUMMYFUNCTION("""COMPUTED_VALUE"""),40987.0) -> 40987 | G38: =IFERROR(__xludf.DUMMYFUNCTION("""COMPUTED_VALUE"""),40577.0) -> 40577 | H38: =IFERROR(__xludf.DUMMYFUNCTION("""COMPUTED_VALUE"""),410.0) -> 410 | I38: =IFERROR(__xludf.DUMMYFUNCTION("""COMPUTED_VALUE"""),"EXCEPTION") -> EXCEPTION | K38: =IFS(J38="Prepayment", "Update schedule, recalculate interest",J38="System Error", "Escalate to tech team",J38="Waiver Applied", "Verify approval, update ledger",J38="Partial Payment", "Contact customer for balance",J38="Rate Change", "Update loan agreement",J38="", "" ) | L38: =VLOOKUP(A38,LMS_Loan_Tape!A:Z,7,FALSE) -> Northern Arc | M38: =D38+H38 -> 410 | N38: =VLOOKUP(A38,LMS_Loan_Tape!A:Z,6,FALSE) -> Business Loan | O38: =VLOOKUP(A38, LMS_Loan_Tape!A37:Z1036,11,false) -> 5
A39: =IFERROR(__xludf.DUMMYFUNCTION("""COMPUTED_VALUE"""),"LN-10135") -> LN-10135 | B39: =IFERROR(__xludf.DUMMYFUNCTION("""COMPUTED_VALUE"""),72617.0) -> 72617 | C39: =IFERROR(__xludf.DUMMYFUNCTION("""COMPUTED_VALUE"""),76247.0) -> 76247 | D39: =IFERROR(__xludf.DUMMYFUNCTION("""COMPUTED_VALUE"""),-3630.0) -> -3630 | E39: =IFERROR(__xludf.DUMMYFUNCTION("""COMPUTED_VALUE"""),-0.04998829475191759) -> -0.049988295 | F39: =IFERROR(__xludf.DUMMYFUNCTION("""COMPUTED_VALUE"""),43451.0) -> 43451 | G39: =IFERROR(__xludf.DUMMYFUNCTION("""COMPUTED_VALUE"""),43451.0) -> 43451 | H39: =IFERROR(__xludf.DUMMYFUNCTION("""COMPUTED_VALUE"""),0.0) -> 0 | I39: =IFERROR(__xludf.DUMMYFUNCTION("""COMPUTED_VALUE"""),"EXCEPTION") -> EXCEPTION | J39: =IFERROR(__xludf.DUMMYFUNCTION("""COMPUTED_VALUE"""),"Rate Change") -> Rate Change | K39: =IFS(J39="Prepayment", "Update schedule, recalculate interest",J39="System Error", "Escalate to tech team",J39="Waiver Applied", "Verify approval, update ledger",J39="Partial Payment", "Contact customer for balance",J39="Rate Change", "Update loan agreement",J39="", "" ) -> Update loan agreement | L39: =VLOOKUP(A39,LMS_Loan_Tape!A:Z,7,FALSE) -> Northern Arc | M39: =D39+H39 -> -3630 | N39: =VLOOKUP(A39,LMS_Loan_Tape!A:Z,6,FALSE) -> Home Loan | O39: =VLOOKUP(A39, LMS_Loan_Tape!A38:Z1037,11,false) -> 2
A40: =IFERROR(__xludf.DUMMYFUNCTION("""COMPUTED_VALUE"""),"LN-10140") -> LN-10140 | B40: =IFERROR(__xludf.DUMMYFUNCTION("""COMPUTED_VALUE"""),134365.0) -> 134365 | C40: =IFERROR(__xludf.DUMMYFUNCTION("""COMPUTED_VALUE"""),131677.0) -> 131677 | D40: =IFERROR(__xludf.DUMMYFUNCTION("""COMPUTED_VALUE"""),2688.0) -> 2688 | E40: =IFERROR(__xludf.DUMMYFUNCTION("""COMPUTED_VALUE"""),0.020005209690023444) -> 0.02000521 | F40: =IFERROR(__xludf.DUMMYFUNCTION("""COMPUTED_VALUE"""),24559.0) -> 24559 | G40: =IFERROR(__xludf.DUMMYFUNCTION("""COMPUTED_VALUE"""),24559.0) -> 24559 | H40: =IFERROR(__xludf.DUMMYFUNCTION("""COMPUTED_VALUE"""),0.0) -> 0 | I40: =IFERROR(__xludf.DUMMYFUNCTION("""COMPUTED_VALUE"""),"EXCEPTION") -> EXCEPTION | K40: =IFS(J40="Prepayment", "Update schedule, recalculate interest",J40="System Error", "Escalate to tech team",J40="Waiver Applied", "Verify approval, update ledger",J40="Partial Payment", "Contact customer for balance",J40="Rate Change", "Update loan agreement",J40="", "" ) | L40: =VLOOKUP(A40,LMS_Loan_Tape!A:Z,7,FALSE) -> DMI | M40: =D40+H40 -> 2688 | N40: =VLOOKUP(A40,LMS_Loan_Tape!A:Z,6,FALSE) -> Personal Loan | O40: =VLOOKUP(A40, LMS_Loan_Tape!A39:Z1038,11,false) -> 10
A41: =IFERROR(__xludf.DUMMYFUNCTION("""COMPUTED_VALUE"""),"LN-10141") -> LN-10141 | B41: =IFERROR(__xludf.DUMMYFUNCTION("""COMPUTED_VALUE"""),26864.0) -> 26864 | C41: =IFERROR(__xludf.DUMMYFUNCTION("""COMPUTED_VALUE"""),24177.0) -> 24177 | D41: =IFERROR(__xludf.DUMMYFUNCTION("""COMPUTED_VALUE"""),2687.0) -> 2687 | E41: =IFERROR(__xludf.DUMMYFUNCTION("""COMPUTED_VALUE"""),0.10002233472304943) -> 0.10002233 | F41: =IFERROR(__xludf.DUMMYFUNCTION("""COMPUTED_VALUE"""),9092.0) -> 9092 | G41: =IFERROR(__xludf.DUMMYFUNCTION("""COMPUTED_VALUE"""),4546.0) -> 4546 | H41: =IFERROR(__xludf.DUMMYFUNCTION("""COMPUTED_VALUE"""),4546.0) -> 4546 | I41: =IFERROR(__xludf.DUMMYFUNCTION("""COMPUTED_VALUE"""),"EXCEPTION") -> EXCEPTION | J41: =IFERROR(__xludf.DUMMYFUNCTION("""COMPUTED_VALUE"""),"Waiver Applied") -> Waiver Applied | K41: =IFS(J41="Prepayment", "Update schedule, recalculate interest",J41="System Error", "Escalate to tech team",J41="Waiver Applied", "Verify approval, update ledger",J41="Partial Payment", "Contact customer for balance",J41="Rate Change", "Update loan agreement",J41="", "" ) -> Verify approval, update ledger | L41: =VLOOKUP(A41,LMS_Loan_Tape!A:Z,7,FALSE) -> DMI | M41: =D41+H41 -> 7233 | N41: =VLOOKUP(A41,LMS_Loan_Tape!A:Z,6,FALSE) -> Business Loan | O41: =VLOOKUP(A41, LMS_Loan_Tape!A40:Z1039,11,false) -> 1
A42: =IFERROR(__xludf.DUMMYFUNCTION("""COMPUTED_VALUE"""),"LN-10147") -> LN-10147 | B42: =IFERROR(__xludf.DUMMYFUNCTION("""COMPUTED_VALUE"""),20030.0) -> 20030 | C42: =IFERROR(__xludf.DUMMYFUNCTION("""COMPUTED_VALUE"""),20030.0) -> 20030 | D42: =IFERROR(__xludf.DUMMYFUNCTION("""COMPUTED_VALUE"""),0.0) -> 0 | E42: =IFERROR(__xludf.DUMMYFUNCTION("""COMPUTED_VALUE"""),0.0) -> 0 | F42: =IFERROR(__xludf.DUMMYFUNCTION("""COMPUTED_VALUE"""),3633.0) -> 3633 | G42: =IFERROR(__xludf.DUMMYFUNCTION("""COMPUTED_VALUE"""),3596.0) -> 3596 | H42: =IFERROR(__xludf.DUMMYFUNCTION("""COMPUTED_VALUE"""),37.0) -> 37 | I42: =IFERROR(__xludf.DUMMYFUNCTION("""COMPUTED_VALUE"""),"EXCEPTION") -> EXCEPTION | K42: =IFS(J42="Prepayment", "Update schedule, recalculate interest",J42="System Error", "Escalate to tech team",J42="Waiver Applied", "Verify approval, update ledger",J42="Partial Payment", "Contact customer for balance",J42="Rate Change", "Update loan agreement",J42="", "" ) | L42: =VLOOKUP(A42,LMS_Loan_Tape!A:Z,7,FALSE) -> Piramal | M42: =D42+H42 -> 37 | N42: =VLOOKUP(A42,LMS_Loan_Tape!A:Z,6,FALSE) -> Home Loan | O42: =VLOOKUP(A42, LMS_Loan_Tape!A41:Z1040,11,false) -> 7
A43: =IFERROR(__xludf.DUMMYFUNCTION("""COMPUTED_VALUE"""),"LN-10151") -> LN-10151 | B43: =IFERROR(__xludf.DUMMYFUNCTION("""COMPUTED_VALUE"""),218076.0) -> 218076 | C43: =IFERROR(__xludf.DUMMYFUNCTION("""COMPUTED_VALUE"""),213714.0) -> 213714 | D43: =IFERROR(__xludf.DUMMYFUNCTION("""COMPUTED_VALUE"""),4362.0) -> 4362 | E43: =IFERROR(__xludf.DUMMYFUNCTION("""COMPUTED_VALUE"""),0.020002201067517746) -> 0.020002201 | F43: =IFERROR(__xludf.DUMMYFUNCTION("""COMPUTED_VALUE"""),21783.0) -> 21783 | G43: =IFERROR(__xludf.DUMMYFUNCTION("""COMPUTED_VALUE"""),21783.0) -> 21783 | H43: =IFERROR(__xludf.DUMMYFUNCTION("""COMPUTED_VALUE"""),0.0) -> 0 | I43: =IFERROR(__xludf.DUMMYFUNCTION("""COMPUTED_VALUE"""),"EXCEPTION") -> EXCEPTION | K43: =IFS(J43="Prepayment", "Update schedule, recalculate interest",J43="System Error", "Escalate to tech team",J43="Waiver Applied", "Verify approval, update ledger",J43="Partial Payment", "Contact customer for balance",J43="Rate Change", "Update loan agreement",J43="", "" ) | L43: =VLOOKUP(A43,LMS_Loan_Tape!A:Z,7,FALSE) -> Piramal | M43: =D43+H43 -> 4362 | N43: =VLOOKUP(A43,LMS_Loan_Tape!A:Z,6,FALSE) -> Business Loan | O43: =VLOOKUP(A43, LMS_Loan_Tape!A42:Z1041,11,false) -> 3
A44: =IFERROR(__xludf.DUMMYFUNCTION("""COMPUTED_VALUE"""),"LN-10157") -> LN-10157 | B44: =IFERROR(__xludf.DUMMYFUNCTION("""COMPUTED_VALUE"""),148836.0) -> 148836 | C44: =IFERROR(__xludf.DUMMYFUNCTION("""COMPUTED_VALUE"""),145859.0) -> 145859 | D44: =IFERROR(__xludf.DUMMYFUNCTION("""COMPUTED_VALUE"""),2977.0) -> 2977 | E44: =IFERROR(__xludf.DUMMYFUNCTION("""COMPUTED_VALUE"""),0.02000188126528528) -> 0.020001881 | F44: =IFERROR(__xludf.DUMMYFUNCTION("""COMPUTED_VALUE"""),15987.0) -> 15987 | G44: =IFERROR(__xludf.DUMMYFUNCTION("""COMPUTED_VALUE"""),15987.0) -> 15987 | H44: =IFERROR(__xludf.DUMMYFUNCTION("""COMPUTED_VALUE"""),0.0) -> 0 | I44: =IFERROR(__xludf.DUMMYFUNCTION("""COMPUTED_VALUE"""),"EXCEPTION") -> EXCEPTION | K44: =IFS(J44="Prepayment", "Update schedule, recalculate interest",J44="System Error", "Escalate to tech team",J44="Waiver Applied", "Verify approval, update ledger",J44="Partial Payment", "Contact customer for balance",J44="Rate Change", "Update loan agreement",J44="", "" ) | L44: =VLOOKUP(A44,LMS_Loan_Tape!A:Z,7,FALSE) -> Tata Capital | M44: =D44+H44 -> 2977 | N44: =VLOOKUP(A44,LMS_Loan_Tape!A:Z,6,FALSE) -> Home Loan | O44: =VLOOKUP(A44, LMS_Loan_Tape!A43:Z1042,11,false) -> 7
A45: =IFERROR(__xludf.DUMMYFUNCTION("""COMPUTED_VALUE"""),"LN-10162") -> LN-10162 | B45: =IFERROR(__xludf.DUMMYFUNCTION("""COMPUTED_VALUE"""),139650.0) -> 139650 | C45: =IFERROR(__xludf.DUMMYFUNCTION("""COMPUTED_VALUE"""),125685.0) -> 125685 | D45: =IFERROR(__xludf.DUMMYFUNCTION("""COMPUTED_VALUE"""),13965.0) -> 13965 | E45: =IFERROR(__xludf.DUMMYFUNCTION("""COMPUTED_VALUE"""),0.1) -> 0.1 | F45: =IFERROR(__xludf.DUMMYFUNCTION("""COMPUTED_VALUE"""),11432.0) -> 11432 | G45: =IFERROR(__xludf.DUMMYFUNCTION("""COMPUTED_VALUE"""),5716.0) -> 5716 | H45: =IFERROR(__xludf.DUMMYFUNCTION("""COMPUTED_VALUE"""),5716.0) -> 5716 | I45: =IFERROR(__xludf.DUMMYFUNCTION("""COMPUTED_VALUE"""),"EXCEPTION") -> EXCEPTION | J45: =IFERROR(__xludf.DUMMYFUNCTION("""COMPUTED_VALUE"""),"Waiver Applied") -> Waiver Applied | K45: =IFS(J45="Prepayment", "Update schedule, recalculate interest",J45="System Error", "Escalate to tech team",J45="Waiver Applied", "Verify approval, update ledger",J45="Partial Payment", "Contact customer for balance",J45="Rate Change", "Update loan agreement",J45="", "" ) -> Verify approval, update ledger | L45: =VLOOKUP(A45,LMS_Loan_Tape!A:Z,7,FALSE) -> Tata Capital | M45: =D45+H45 -> 19681 | N45: =VLOOKUP(A45,LMS_Loan_Tape!A:Z,6,FALSE) -> Personal Loan | O45: =VLOOKUP(A45, LMS_Loan_Tape!A44:Z1043,11,false) -> 12
A46: =IFERROR(__xludf.DUMMYFUNCTION("""COMPUTED_VALUE"""),"LN-10166") -> LN-10166 | B46: =IFERROR(__xludf.DUMMYFUNCTION("""COMPUTED_VALUE"""),24798.0) -> 24798 | C46: =IFERROR(__xludf.DUMMYFUNCTION("""COMPUTED_VALUE"""),24798.0) -> 24798 | D46: =IFERROR(__xludf.DUMMYFUNCTION("""COMPUTED_VALUE"""),0.0) -> 0 | E46: =IFERROR(__xludf.DUMMYFUNCTION("""COMPUTED_VALUE"""),0.0) -> 0 | F46: =IFERROR(__xludf.DUMMYFUNCTION("""COMPUTED_VALUE"""),5843.0) -> 5843 | G46: =IFERROR(__xludf.DUMMYFUNCTION("""COMPUTED_VALUE"""),5784.0) -> 5784 | H46: =IFERROR(__xludf.DUMMYFUNCTION("""COMPUTED_VALUE"""),59.0) -> 59 | I46: =IFERROR(__xludf.DUMMYFUNCTION("""COMPUTED_VALUE"""),"EXCEPTION") -> EXCEPTION | K46: =IFS(J46="Prepayment", "Update schedule, recalculate interest",J46="System Error", "Escalate to tech team",J46="Waiver Applied", "Verify approval, update ledger",J46="Partial Payment", "Contact customer for balance",J46="Rate Change", "Update loan agreement",J46="", "" ) | L46: =VLOOKUP(A46,LMS_Loan_Tape!A:Z,7,FALSE) -> Tata Capital | M46: =D46+H46 -> 59 | N46: =VLOOKUP(A46,LMS_Loan_Tape!A:Z,6,FALSE) -> Home Loan | O46: =VLOOKUP(A46, LMS_Loan_Tape!A45:Z1044,11,false) -> 8
A47: =IFERROR(__xludf.DUMMYFUNCTION("""COMPUTED_VALUE"""),"LN-10172") -> LN-10172 | B47: =IFERROR(__xludf.DUMMYFUNCTION("""COMPUTED_VALUE"""),136590.0) -> 136590 | C47: =IFERROR(__xludf.DUMMYFUNCTION("""COMPUTED_VALUE"""),133858.0) -> 133858 | D47: =IFERROR(__xludf.DUMMYFUNCTION("""COMPUTED_VALUE"""),2732.0) -> 2732 | E47: =IFERROR(__xludf.DUMMYFUNCTION("""COMPUTED_VALUE"""),0.020001464236034848) -> 0.020001464 | F47: =IFERROR(__xludf.DUMMYFUNCTION("""COMPUTED_VALUE"""),20542.0) -> 20542 | G47: =IFERROR(__xludf.DUMMYFUNCTION("""COMPUTED_VALUE"""),20336.0) -> 20336 | H47: =IFERROR(__xludf.DUMMYFUNCTION("""COMPUTED_VALUE"""),206.0) -> 206 | I47: =IFERROR(__xludf.DUMMYFUNCTION("""COMPUTED_VALUE"""),"EXCEPTION") -> EXCEPTION | K47: =IFS(J47="Prepayment", "Update schedule, recalculate interest",J47="System Error", "Escalate to tech team",J47="Waiver Applied", "Verify approval, update ledger",J47="Partial Payment", "Contact customer for balance",J47="Rate Change", "Update loan agreement",J47="", "" ) | L47: =VLOOKUP(A47,LMS_Loan_Tape!A:Z,7,FALSE) -> DMI | M47: =D47+H47 -> 2938 | N47: =VLOOKUP(A47,LMS_Loan_Tape!A:Z,6,FALSE) -> Home Loan | O47: =VLOOKUP(A47, LMS_Loan_Tape!A46:Z1045,11,false) -> 12
A48: =IFERROR(__xludf.DUMMYFUNCTION("""COMPUTED_VALUE"""),"LN-10174") -> LN-10174 | B48: =IFERROR(__xludf.DUMMYFUNCTION("""COMPUTED_VALUE"""),178739.0) -> 178739 | C48: =IFERROR(__xludf.DUMMYFUNCTION("""COMPUTED_VALUE"""),178869.0) -> 178869 | D48: =IFERROR(__xludf.DUMMYFUNCTION("""COMPUTED_VALUE"""),-130.0) -> -130 | E48: =IFERROR(__xludf.DUMMYFUNCTION("""COMPUTED_VALUE"""),-7.273174852718209E-4) -> -0.00072731749 | F48: =IFERROR(__xludf.DUMMYFUNCTION("""COMPUTED_VALUE"""),29609.0) -> 29609 | G48: =IFERROR(__xludf.DUMMYFUNCTION("""COMPUTED_VALUE"""),29609.0) -> 29609 | H48: =IFERROR(__xludf.DUMMYFUNCTION("""COMPUTED_VALUE"""),0.0) -> 0 | I48: =IFERROR(__xludf.DUMMYFUNCTION("""COMPUTED_VALUE"""),"EXCEPTION") -> EXCEPTION | J48: =IFERROR(__xludf.DUMMYFUNCTION("""COMPUTED_VALUE"""),"System Error") -> System Error | K48: =IFS(J48="Prepayment", "Update schedule, recalculate interest",J48="System Error", "Escalate to tech team",J48="Waiver Applied", "Verify approval, update ledger",J48="Partial Payment", "Contact customer for balance",J48="Rate Change", "Update loan agreement",J48="", "" ) -> Escalate to tech team | L48: =VLOOKUP(A48,LMS_Loan_Tape!A:Z,7,FALSE) -> Piramal | M48: =D48+H48 -> -130 | N48: =VLOOKUP(A48,LMS_Loan_Tape!A:Z,6,FALSE) -> Business Loan | O48: =VLOOKUP(A48, LMS_Loan_Tape!A47:Z1046,11,false) -> 6
A49: =IFERROR(__xludf.DUMMYFUNCTION("""COMPUTED_VALUE"""),"LN-10180") -> LN-10180 | B49: =IFERROR(__xludf.DUMMYFUNCTION("""COMPUTED_VALUE"""),79336.0) -> 79336 | C49: =IFERROR(__xludf.DUMMYFUNCTION("""COMPUTED_VALUE"""),80135.0) -> 80135 | D49: =IFERROR(__xludf.DUMMYFUNCTION("""COMPUTED_VALUE"""),-799.0) -> -799 | E49: =IFERROR(__xludf.DUMMYFUNCTION("""COMPUTED_VALUE"""),-0.010071090047393365) -> -0.01007109 | F49: =IFERROR(__xludf.DUMMYFUNCTION("""COMPUTED_VALUE"""),30727.0) -> 30727 | G49: =IFERROR(__xludf.DUMMYFUNCTION("""COMPUTED_VALUE"""),30727.0) -> 30727 | H49: =IFERROR(__xludf.DUMMYFUNCTION("""COMPUTED_VALUE"""),0.0) -> 0 | I49: =IFERROR(__xludf.DUMMYFUNCTION("""COMPUTED_VALUE"""),"EXCEPTION") -> EXCEPTION | J49: =IFERROR(__xludf.DUMMYFUNCTION("""COMPUTED_VALUE"""),"System Error") -> System Error | K49: =IFS(J49="Prepayment", "Update schedule, recalculate interest",J49="System Error", "Escalate to tech team",J49="Waiver Applied", "Verify approval, update ledger",J49="Partial Payment", "Contact customer for balance",J49="Rate Change", "Update loan agreement",J49="", "" ) -> Escalate to tech team | L49: =VLOOKUP(A49,LMS_Loan_Tape!A:Z,7,FALSE) -> Liquiloans | M49: =D49+H49 -> -799 | N49: =VLOOKUP(A49,LMS_Loan_Tape!A:Z,6,FALSE) -> Gold Loan | O49: =VLOOKUP(A49, LMS_Loan_Tape!A48:Z1047,11,false) -> 1
A50: =IFERROR(__xludf.DUMMYFUNCTION("""COMPUTED_VALUE"""),"LN-10194") -> LN-10194 | B50: =IFERROR(__xludf.DUMMYFUNCTION("""COMPUTED_VALUE"""),27266.0) -> 27266 | C50: =IFERROR(__xludf.DUMMYFUNCTION("""COMPUTED_VALUE"""),28629.0) -> 28629 | D50: =IFERROR(__xludf.DUMMYFUNCTION("""COMPUTED_VALUE"""),-1363.0) -> -1363 | E50: =IFERROR(__xludf.DUMMYFUNCTION("""COMPUTED_VALUE"""),-0.04998899728599721) -> -0.049988997 | F50: =IFERROR(__xludf.DUMMYFUNCTION("""COMPUTED_VALUE"""),12880.0) -> 12880 | G50: =IFERROR(__xludf.DUMMYFUNCTION("""COMPUTED_VALUE"""),12880.0) -> 12880 | H50: =IFERROR(__xludf.DUMMYFUNCTION("""COMPUTED_VALUE"""),0.0) -> 0 | I50: =IFERROR(__xludf.DUMMYFUNCTION("""COMPUTED_VALUE"""),"EXCEPTION") -> EXCEPTION | J50: =IFERROR(__xludf.DUMMYFUNCTION("""COMPUTED_VALUE"""),"Rate Change") -> Rate Change | K50: =IFS(J50="Prepayment", "Update schedule, recalculate interest",J50="System Error", "Escalate to tech team",J50="Waiver Applied", "Verify approval, update ledger",J50="Partial Payment", "Contact customer for balance",J50="Rate Change", "Update loan agreement",J50="", "" ) -> Update loan agreement | L50: =VLOOKUP(A50,LMS_Loan_Tape!A:Z,7,FALSE) -> DMI | M50: =D50+H50 -> -1363 | N50: =VLOOKUP(A50,LMS_Loan_Tape!A:Z,6,FALSE) -> Business Loan | O50: =VLOOKUP(A50, LMS_Loan_Tape!A49:Z1048,11,false) -> 2
A51: =IFERROR(__xludf.DUMMYFUNCTION("""COMPUTED_VALUE"""),"LN-10196") -> LN-10196 | B51: =IFERROR(__xludf.DUMMYFUNCTION("""COMPUTED_VALUE"""),96653.0) -> 96653 | C51: =IFERROR(__xludf.DUMMYFUNCTION("""COMPUTED_VALUE"""),94719.0) -> 94719 | D51: =IFERROR(__xludf.DUMMYFUNCTION("""COMPUTED_VALUE"""),1934.0) -> 1934 | E51: =IFERROR(__xludf.DUMMYFUNCTION("""COMPUTED_VALUE"""),0.020009725512917343) -> 0.020009726 | F51: =IFERROR(__xludf.DUMMYFUNCTION("""COMPUTED_VALUE"""),10718.0) -> 10718 | G51: =IFERROR(__xludf.DUMMYFUNCTION("""COMPUTED_VALUE"""),10718.0) -> 10718 | H51: =IFERROR(__xludf.DUMMYFUNCTION("""COMPUTED_VALUE"""),0.0) -> 0 | I51: =IFERROR(__xludf.DUMMYFUNCTION("""COMPUTED_VALUE"""),"EXCEPTION") -> EXCEPTION | K51: =IFS(J51="Prepayment", "Update schedule, recalculate interest",J51="System Error", "Escalate to tech team",J51="Waiver Applied", "Verify approval, update ledger",J51="Partial Payment", "Contact customer for balance",J51="Rate Change", "Update loan agreement",J51="", "" ) | L51: =VLOOKUP(A51,LMS_Loan_Tape!A:Z,7,FALSE) -> DMI | M51: =D51+H51 -> 1934 | N51: =VLOOKUP(A51,LMS_Loan_Tape!A:Z,6,FALSE) -> Business Loan | O51: =VLOOKUP(A51, LMS_Loan_Tape!A50:Z1049,11,false) -> 3
A52: =IFERROR(__xludf.DUMMYFUNCTION("""COMPUTED_VALUE"""),"LN-10203") -> LN-10203 | B52: =IFERROR(__xludf.DUMMYFUNCTION("""COMPUTED_VALUE"""),37186.0) -> 37186 | C52: =IFERROR(__xludf.DUMMYFUNCTION("""COMPUTED_VALUE"""),29748.0) -> 29748 | D52: =IFERROR(__xludf.DUMMYFUNCTION("""COMPUTED_VALUE"""),7438.0) -> 7438 | E52: =IFERROR(__xludf.DUMMYFUNCTION("""COMPUTED_VALUE"""),0.20002151347281236) -> 0.20002151 | F52: =IFERROR(__xludf.DUMMYFUNCTION("""COMPUTED_VALUE"""),9906.0) -> 9906 | G52: =IFERROR(__xludf.DUMMYFUNCTION("""COMPUTED_VALUE"""),9906.0) -> 9906 | H52: =IFERROR(__xludf.DUMMYFUNCTION("""COMPUTED_VALUE"""),0.0) -> 0 | I52: =IFERROR(__xludf.DUMMYFUNCTION("""COMPUTED_VALUE"""),"EXCEPTION") -> EXCEPTION | J52: =IFERROR(__xludf.DUMMYFUNCTION("""COMPUTED_VALUE"""),"Prepayment") -> Prepayment | K52: =IFS(J52="Prepayment", "Update schedule, recalculate interest",J52="System Error", "Escalate to tech team",J52="Waiver Applied", "Verify approval, update ledger",J52="Partial Payment", "Contact customer for balance",J52="Rate Change", "Update loan agreement",J52="", "" ) -> Update schedule, recalculate interest | L52: =VLOOKUP(A52,LMS_Loan_Tape!A:Z,7,FALSE) -> DMI | M52: =D52+H52 -> 7438 | N52: =VLOOKUP(A52,LMS_Loan_Tape!A:Z,6,FALSE) -> Personal Loan | O52: =VLOOKUP(A52, LMS_Loan_Tape!A51:Z1050,11,false) -> 12
A53: =IFERROR(__xludf.DUMMYFUNCTION("""COMPUTED_VALUE"""),"LN-10204") -> LN-10204 | B53: =IFERROR(__xludf.DUMMYFUNCTION("""COMPUTED_VALUE"""),106109.0) -> 106109 | C53: =IFERROR(__xludf.DUMMYFUNCTION("""COMPUTED_VALUE"""),106109.0) -> 106109 | D53: =IFERROR(__xludf.DUMMYFUNCTION("""COMPUTED_VALUE"""),0.0) -> 0 | E53: =IFERROR(__xludf.DUMMYFUNCTION("""COMPUTED_VALUE"""),0.0) -> 0 | F53: =IFERROR(__xludf.DUMMYFUNCTION("""COMPUTED_VALUE"""),14993.0) -> 14993 | G53: =IFERROR(__xludf.DUMMYFUNCTION("""COMPUTED_VALUE"""),14843.0) -> 14843 | H53: =IFERROR(__xludf.DUMMYFUNCTION("""COMPUTED_VALUE"""),150.0) -> 150 | I53: =IFERROR(__xludf.DUMMYFUNCTION("""COMPUTED_VALUE"""),"EXCEPTION") -> EXCEPTION | K53: =IFS(J53="Prepayment", "Update schedule, recalculate interest",J53="System Error", "Escalate to tech team",J53="Waiver Applied", "Verify approval, update ledger",J53="Partial Payment", "Contact customer for balance",J53="Rate Change", "Update loan agreement",J53="", "" ) | L53: =VLOOKUP(A53,LMS_Loan_Tape!A:Z,7,FALSE) -> Tata Capital | M53: =D53+H53 -> 150 | N53: =VLOOKUP(A53,LMS_Loan_Tape!A:Z,6,FALSE) -> Home Loan | O53: =VLOOKUP(A53, LMS_Loan_Tape!A52:Z1051,11,false) -> 7
A54: =IFERROR(__xludf.DUMMYFUNCTION("""COMPUTED_VALUE"""),"LN-10208") -> LN-10208 | B54: =IFERROR(__xludf.DUMMYFUNCTION("""COMPUTED_VALUE"""),424966.0) -> 424966 | C54: =IFERROR(__xludf.DUMMYFUNCTION("""COMPUTED_VALUE"""),254979.0) -> 254979 | D54: =IFERROR(__xludf.DUMMYFUNCTION("""COMPUTED_VALUE"""),169987.0) -> 169987 | E54: =IFERROR(__xludf.DUMMYFUNCTION("""COMPUTED_VALUE"""),0.4000014118776561) -> 0.40000141 | F54: =IFERROR(__xludf.DUMMYFUNCTION("""COMPUTED_VALUE"""),29131.0) -> 29131 | G54: =IFERROR(__xludf.DUMMYFUNCTION("""COMPUTED_VALUE"""),29131.0) -> 29131 | H54: =IFERROR(__xludf.DUMMYFUNCTION("""COMPUTED_VALUE"""),0.0) -> 0 | I54: =IFERROR(__xludf.DUMMYFUNCTION("""COMPUTED_VALUE"""),"EXCEPTION") -> EXCEPTION | J54: =IFERROR(__xludf.DUMMYFUNCTION("""COMPUTED_VALUE"""),"Partial Payment") -> Partial Payment | K54: =IFS(J54="Prepayment", "Update schedule, recalculate interest",J54="System Error", "Escalate to tech team",J54="Waiver Applied", "Verify approval, update ledger",J54="Partial Payment", "Contact customer for balance",J54="Rate Change", "Update loan agreement",J54="", "" ) -> Contact customer for balance | L54: =VLOOKUP(A54,LMS_Loan_Tape!A:Z,7,FALSE) -> Liquiloans | M54: =D54+H54 -> 169987 | N54: =VLOOKUP(A54,LMS_Loan_Tape!A:Z,6,FALSE) -> Home Loan | O54: =VLOOKUP(A54, LMS_Loan_Tape!A53:Z1052,11,false) -> 5
A55: =IFERROR(__xludf.DUMMYFUNCTION("""COMPUTED_VALUE"""),"LN-10210") -> LN-10210 | B55: =IFERROR(__xludf.DUMMYFUNCTION("""COMPUTED_VALUE"""),197606.0) -> 197606 | C55: =IFERROR(__xludf.DUMMYFUNCTION("""COMPUTED_VALUE"""),197606.0) -> 197606 | D55: =IFERROR(__xludf.DUMMYFUNCTION("""COMPUTED_VALUE"""),0.0) -> 0 | E55: =IFERROR(__xludf.DUMMYFUNCTION("""COMPUTED_VALUE"""),0.0) -> 0 | F55: =IFERROR(__xludf.DUMMYFUNCTION("""COMPUTED_VALUE"""),22571.0) -> 22571 | G55: =IFERROR(__xludf.DUMMYFUNCTION("""COMPUTED_VALUE"""),22345.0) -> 22345 | H55: =IFERROR(__xludf.DUMMYFUNCTION("""COMPUTED_VALUE"""),226.0) -> 226 | I55: =IFERROR(__xludf.DUMMYFUNCTION("""COMPUTED_VALUE"""),"EXCEPTION") -> EXCEPTION | K55: =IFS(J55="Prepayment", "Update schedule, recalculate interest",J55="System Error", "Escalate to tech team",J55="Waiver Applied", "Verify approval, update ledger",J55="Partial Payment", "Contact customer for balance",J55="Rate Change", "Update loan agreement",J55="", "" ) | L55: =VLOOKUP(A55,LMS_Loan_Tape!A:Z,7,FALSE) -> Tata Capital | M55: =D55+H55 -> 226 | N55: =VLOOKUP(A55,LMS_Loan_Tape!A:Z,6,FALSE) -> Home Loan | O55: =VLOOKUP(A55, LMS_Loan_Tape!A54:Z1053,11,false) -> 4
A56: =IFERROR(__xludf.DUMMYFUNCTION("""COMPUTED_VALUE"""),"LN-10212") -> LN-10212 | B56: =IFERROR(__xludf.DUMMYFUNCTION("""COMPUTED_VALUE"""),67038.0) -> 67038 | C56: =IFERROR(__xludf.DUMMYFUNCTION("""COMPUTED_VALUE"""),67841.0) -> 67841 | D56: =IFERROR(__xludf.DUMMYFUNCTION("""COMPUTED_VALUE"""),-803.0) -> -803 | E56: =IFERROR(__xludf.DUMMYFUNCTION("""COMPUTED_VALUE"""),-0.01197828097496942) -> -0.011978281 | F56: =IFERROR(__xludf.DUMMYFUNCTION("""COMPUTED_VALUE"""),13763.0) -> 13763 | G56: =IFERROR(__xludf.DUMMYFUNCTION("""COMPUTED_VALUE"""),13763.0) -> 13763 | H56: =IFERROR(__xludf.DUMMYFUNCTION("""COMPUTED_VALUE"""),0.0) -> 0 | I56: =IFERROR(__xludf.DUMMYFUNCTION("""COMPUTED_VALUE"""),"EXCEPTION") -> EXCEPTION | J56: =IFERROR(__xludf.DUMMYFUNCTION("""COMPUTED_VALUE"""),"System Error") -> System Error | K56: =IFS(J56="Prepayment", "Update schedule, recalculate interest",J56="System Error", "Escalate to tech team",J56="Waiver Applied", "Verify approval, update ledger",J56="Partial Payment", "Contact customer for balance",J56="Rate Change", "Update loan agreement",J56="", "" ) -> Escalate to tech team | L56: =VLOOKUP(A56,LMS_Loan_Tape!A:Z,7,FALSE) -> Tata Capital | M56: =D56+H56 -> -803 | N56: =VLOOKUP(A56,LMS_Loan_Tape!A:Z,6,FALSE) -> Home Loan | O56: =VLOOKUP(A56, LMS_Loan_Tape!A55:Z1054,11,false) -> 1
A57: =IFERROR(__xludf.DUMMYFUNCTION("""COMPUTED_VALUE"""),"LN-10213") -> LN-10213 | B57: =IFERROR(__xludf.DUMMYFUNCTION("""COMPUTED_VALUE"""),264467.0) -> 264467 | C57: =IFERROR(__xludf.DUMMYFUNCTION("""COMPUTED_VALUE"""),158680.0) -> 158680 | D57: =IFERROR(__xludf.DUMMYFUNCTION("""COMPUTED_VALUE"""),105787.0) -> 105787 | E57: =IFERROR(__xludf.DUMMYFUNCTION("""COMPUTED_VALUE"""),0.40000075623801834) -> 0.40000076 | F57: =IFERROR(__xludf.DUMMYFUNCTION("""COMPUTED_VALUE"""),46667.0) -> 46667 | G57: =IFERROR(__xludf.DUMMYFUNCTION("""COMPUTED_VALUE"""),46667.0) -> 46667 | H57: =IFERROR(__xludf.DUMMYFUNCTION("""COMPUTED_VALUE"""),0.0) -> 0 | I57: =IFERROR(__xludf.DUMMYFUNCTION("""COMPUTED_VALUE"""),"EXCEPTION") -> EXCEPTION | J57: =IFERROR(__xludf.DUMMYFUNCTION("""COMPUTED_VALUE"""),"Partial Payment") -> Partial Payment | K57: =IFS(J57="Prepayment", "Update schedule, recalculate interest",J57="System Error", "Escalate to tech team",J57="Waiver Applied", "Verify approval, update ledger",J57="Partial Payment", "Contact customer for balance",J57="Rate Change", "Update loan agreement",J57="", "" ) -> Contact customer for balance | L57: =VLOOKUP(A57,LMS_Loan_Tape!A:Z,7,FALSE) -> DMI | M57: =D57+H57 -> 105787 | N57: =VLOOKUP(A57,LMS_Loan_Tape!A:Z,6,FALSE) -> Home Loan | O57: =VLOOKUP(A57, LMS_Loan_Tape!A56:Z1055,11,false) -> 1
A58: =IFERROR(__xludf.DUMMYFUNCTION("""COMPUTED_VALUE"""),"LN-10218") -> LN-10218 | B58: =IFERROR(__xludf.DUMMYFUNCTION("""COMPUTED_VALUE"""),182595.0) -> 182595 | C58: =IFERROR(__xludf.DUMMYFUNCTION("""COMPUTED_VALUE"""),183322.0) -> 183322 | D58: =IFERROR(__xludf.DUMMYFUNCTION("""COMPUTED_VALUE"""),-727.0) -> -727 | E58: =IFERROR(__xludf.DUMMYFUNCTION("""COMPUTED_VALUE"""),-0.003981489087872067) -> -0.0039814891 | F58: =IFERROR(__xludf.DUMMYFUNCTION("""COMPUTED_VALUE"""),37654.0) -> 37654 | G58: =IFERROR(__xludf.DUMMYFUNCTION("""COMPUTED_VALUE"""),37654.0) -> 37654 | H58: =IFERROR(__xludf.DUMMYFUNCTION("""COMPUTED_VALUE"""),0.0) -> 0 | I58: =IFERROR(__xludf.DUMMYFUNCTION("""COMPUTED_VALUE"""),"EXCEPTION") -> EXCEPTION | J58: =IFERROR(__xludf.DUMMYFUNCTION("""COMPUTED_VALUE"""),"System Error") -> System Error | K58: =IFS(J58="Prepayment", "Update schedule, recalculate interest",J58="System Error", "Escalate to tech team",J58="Waiver Applied", "Verify approval, update ledger",J58="Partial Payment", "Contact customer for balance",J58="Rate Change", "Update loan agreement",J58="", "" ) -> Escalate to tech team | L58: =VLOOKUP(A58,LMS_Loan_Tape!A:Z,7,FALSE) -> Liquiloans | M58: =D58+H58 -> -727 | N58: =VLOOKUP(A58,LMS_Loan_Tape!A:Z,6,FALSE) -> Gold Loan | O58: =VLOOKUP(A58, LMS_Loan_Tape!A57:Z1056,11,false) -> 11
A59: =IFERROR(__xludf.DUMMYFUNCTION("""COMPUTED_VALUE"""),"LN-10220") -> LN-10220 | B59: =IFERROR(__xludf.DUMMYFUNCTION("""COMPUTED_VALUE"""),174227.0) -> 174227 | C59: =IFERROR(__xludf.DUMMYFUNCTION("""COMPUTED_VALUE"""),174818.0) -> 174818 | D59: =IFERROR(__xludf.DUMMYFUNCTION("""COMPUTED_VALUE"""),-591.0) -> -591 | E59: =IFERROR(__xludf.DUMMYFUNCTION("""COMPUTED_VALUE"""),-0.003392126363881603) -> -0.0033921264 | F59: =IFERROR(__xludf.DUMMYFUNCTION("""COMPUTED_VALUE"""),16761.0) -> 16761 | G59: =IFERROR(__xludf.DUMMYFUNCTION("""COMPUTED_VALUE"""),16761.0) -> 16761 | H59: =IFERROR(__xludf.DUMMYFUNCTION("""COMPUTED_VALUE"""),0.0) -> 0 | I59: =IFERROR(__xludf.DUMMYFUNCTION("""COMPUTED_VALUE"""),"EXCEPTION") -> EXCEPTION | J59: =IFERROR(__xludf.DUMMYFUNCTION("""COMPUTED_VALUE"""),"System Error") -> System Error | K59: =IFS(J59="Prepayment", "Update schedule, recalculate interest",J59="System Error", "Escalate to tech team",J59="Waiver Applied", "Verify approval, update ledger",J59="Partial Payment", "Contact customer for balance",J59="Rate Change", "Update loan agreement",J59="", "" ) -> Escalate to tech team | L59: =VLOOKUP(A59,LMS_Loan_Tape!A:Z,7,FALSE) -> Northern Arc | M59: =D59+H59 -> -591 | N59: =VLOOKUP(A59,LMS_Loan_Tape!A:Z,6,FALSE) -> Business Loan | O59: =VLOOKUP(A59, LMS_Loan_Tape!A58:Z1057,11,false) -> 6
A60: =IFERROR(__xludf.DUMMYFUNCTION("""COMPUTED_VALUE"""),"LN-10223") -> LN-10223 | B60: =IFERROR(__xludf.DUMMYFUNCTION("""COMPUTED_VALUE"""),95059.0) -> 95059 | C60: =IFERROR(__xludf.DUMMYFUNCTION("""COMPUTED_VALUE"""),85553.0) -> 85553 | D60: =IFERROR(__xludf.DUMMYFUNCTION("""COMPUTED_VALUE"""),9506.0) -> 9506 | E60: =IFERROR(__xludf.DUMMYFUNCTION("""COMPUTED_VALUE"""),0.10000105197824509) -> 0.10000105 | F60: =IFERROR(__xludf.DUMMYFUNCTION("""COMPUTED_VALUE"""),16553.0) -> 16553 | G60: =IFERROR(__xludf.DUMMYFUNCTION("""COMPUTED_VALUE"""),8276.0) -> 8276 | H60: =IFERROR(__xludf.DUMMYFUNCTION("""COMPUTED_VALUE"""),8277.0) -> 8277 | I60: =IFERROR(__xludf.DUMMYFUNCTION("""COMPUTED_VALUE"""),"EXCEPTION") -> EXCEPTION | J60: =IFERROR(__xludf.DUMMYFUNCTION("""COMPUTED_VALUE"""),"Waiver Applied") -> Waiver Applied | K60: =IFS(J60="Prepayment", "Update schedule, recalculate interest",J60="System Error", "Escalate to tech team",J60="Waiver Applied", "Verify approval, update ledger",J60="Partial Payment", "Contact customer for balance",J60="Rate Change", "Update loan agreement",J60="", "" ) -> Verify approval, update ledger | L60: =VLOOKUP(A60,LMS_Loan_Tape!A:Z,7,FALSE) -> Liquiloans | M60: =D60+H60 -> 17783 | N60: =VLOOKUP(A60,LMS_Loan_Tape!A:Z,6,FALSE) -> Personal Loan | O60: =VLOOKUP(A60, LMS_Loan_Tape!A59:Z1058,11,false) -> 12
A61: =IFERROR(__xludf.DUMMYFUNCTION("""COMPUTED_VALUE"""),"LN-10224") -> LN-10224 | B61: =IFERROR(__xludf.DUMMYFUNCTION("""COMPUTED_VALUE"""),55054.0) -> 55054 | C61: =IFERROR(__xludf.DUMMYFUNCTION("""COMPUTED_VALUE"""),57806.0) -> 57806 | D61: =IFERROR(__xludf.DUMMYFUNCTION("""COMPUTED_VALUE"""),-2752.0) -> -2752 | E61: =IFERROR(__xludf.DUMMYFUNCTION("""COMPUTED_VALUE"""),-0.04998728521088386) -> -0.049987285 | F61: =IFERROR(__xludf.DUMMYFUNCTION("""COMPUTED_VALUE"""),14790.0) -> 14790 | G61: =IFERROR(__xludf.DUMMYFUNCTION("""COMPUTED_VALUE"""),14790.0) -> 14790 | H61: =IFERROR(__xludf.DUMMYFUNCTION("""COMPUTED_VALUE"""),0.0) -> 0 | I61: =IFERROR(__xludf.DUMMYFUNCTION("""COMPUTED_VALUE"""),"EXCEPTION") -> EXCEPTION | J61: =IFERROR(__xludf.DUMMYFUNCTION("""COMPUTED_VALUE"""),"Rate Change") -> Rate Change | K61: =IFS(J61="Prepayment", "Update schedule, recalculate interest",J61="System Error", "Escalate to tech team",J61="Waiver Applied", "Verify approval, update ledger",J61="Partial Payment", "Contact customer for balance",J61="Rate Change", "Update loan agreement",J61="", "" ) -> Update loan agreement | L61: =VLOOKUP(A61,LMS_Loan_Tape!A:Z,7,FALSE) -> Liquiloans | M61: =D61+H61 -> -2752 | N61: =VLOOKUP(A61,LMS_Loan_Tape!A:Z,6,FALSE) -> Personal Loan | O61: =VLOOKUP(A61, LMS_Loan_Tape!A60:Z1059,11,false) -> 12
A62: =IFERROR(__xludf.DUMMYFUNCTION("""COMPUTED_VALUE"""),"LN-10229") -> LN-10229 | B62: =IFERROR(__xludf.DUMMYFUNCTION("""COMPUTED_VALUE"""),111104.0) -> 111104 | C62: =IFERROR(__xludf.DUMMYFUNCTION("""COMPUTED_VALUE"""),66662.0) -> 66662 | D62: =IFERROR(__xludf.DUMMYFUNCTION("""COMPUTED_VALUE"""),44442.0) -> 44442 | E62: =IFERROR(__xludf.DUMMYFUNCTION("""COMPUTED_VALUE"""),0.40000360023041476) -> 0.4000036 | F62: =IFERROR(__xludf.DUMMYFUNCTION("""COMPUTED_VALUE"""),23932.0) -> 23932 | G62: =IFERROR(__xludf.DUMMYFUNCTION("""COMPUTED_VALUE"""),23932.0) -> 23932 | H62: =IFERROR(__xludf.DUMMYFUNCTION("""COMPUTED_VALUE"""),0.0) -> 0 | I62: =IFERROR(__xludf.DUMMYFUNCTION("""COMPUTED_VALUE"""),"EXCEPTION") -> EXCEPTION | J62: =IFERROR(__xludf.DUMMYFUNCTION("""COMPUTED_VALUE"""),"Partial Payment") -> Partial Payment | K62: =IFS(J62="Prepayment", "Update schedule, recalculate interest",J62="System Error", "Escalate to tech team",J62="Waiver Applied", "Verify approval, update ledger",J62="Partial Payment", "Contact customer for balance",J62="Rate Change", "Update loan agreement",J62="", "" ) -> Contact customer for balance | L62: =VLOOKUP(A62,LMS_Loan_Tape!A:Z,7,FALSE) -> Piramal | M62: =D62+H62 -> 44442 | N62: =VLOOKUP(A62,LMS_Loan_Tape!A:Z,6,FALSE) -> Gold Loan | O62: =VLOOKUP(A62, LMS_Loan_Tape!A61:Z1060,11,false) -> 10
A63: =IFERROR(__xludf.DUMMYFUNCTION("""COMPUTED_VALUE"""),"LN-10230") -> LN-10230 | B63: =IFERROR(__xludf.DUMMYFUNCTION("""COMPUTED_VALUE"""),61370.0) -> 61370 | C63: =IFERROR(__xludf.DUMMYFUNCTION("""COMPUTED_VALUE"""),61784.0) -> 61784 | D63: =IFERROR(__xludf.DUMMYFUNCTION("""COMPUTED_VALUE"""),-414.0) -> -414 | E63: =IFERROR(__xludf.DUMMYFUNCTION("""COMPUTED_VALUE"""),-0.0067459670848948996) -> -0.0067459671 | F63: =IFERROR(__xludf.DUMMYFUNCTION("""COMPUTED_VALUE"""),4701.0) -> 4701 | G63: =IFERROR(__xludf.DUMMYFUNCTION("""COMPUTED_VALUE"""),4701.0) -> 4701 | H63: =IFERROR(__xludf.DUMMYFUNCTION("""COMPUTED_VALUE"""),0.0) -> 0 | I63: =IFERROR(__xludf.DUMMYFUNCTION("""COMPUTED_VALUE"""),"EXCEPTION") -> EXCEPTION | J63: =IFERROR(__xludf.DUMMYFUNCTION("""COMPUTED_VALUE"""),"System Error") -> System Error | K63: =IFS(J63="Prepayment", "Update schedule, recalculate interest",J63="System Error", "Escalate to tech team",J63="Waiver Applied", "Verify approval, update ledger",J63="Partial Payment", "Contact customer for balance",J63="Rate Change", "Update loan agreement",J63="", "" ) -> Escalate to tech team | L63: =VLOOKUP(A63,LMS_Loan_Tape!A:Z,7,FALSE) -> DMI | M63: =D63+H63 -> -414 | N63: =VLOOKUP(A63,LMS_Loan_Tape!A:Z,6,FALSE) -> Home Loan | O63: =VLOOKUP(A63, LMS_Loan_Tape!A62:Z1061,11,false) -> 2
A64: =IFERROR(__xludf.DUMMYFUNCTION("""COMPUTED_VALUE"""),"LN-10231") -> LN-10231 | B64: =IFERROR(__xludf.DUMMYFUNCTION("""COMPUTED_VALUE"""),69133.0) -> 69133 | C64: =IFERROR(__xludf.DUMMYFUNCTION("""COMPUTED_VALUE"""),69133.0) -> 69133 | D64: =IFERROR(__xludf.DUMMYFUNCTION("""COMPUTED_VALUE"""),0.0) -> 0 | E64: =IFERROR(__xludf.DUMMYFUNCTION("""COMPUTED_VALUE"""),0.0) -> 0 | F64: =IFERROR(__xludf.DUMMYFUNCTION("""COMPUTED_VALUE"""),11394.0) -> 11394 | G64: =IFERROR(__xludf.DUMMYFUNCTION("""COMPUTED_VALUE"""),11280.0) -> 11280 | H64: =IFERROR(__xludf.DUMMYFUNCTION("""COMPUTED_VALUE"""),114.0) -> 114 | I64: =IFERROR(__xludf.DUMMYFUNCTION("""COMPUTED_VALUE"""),"EXCEPTION") -> EXCEPTION | K64: =IFS(J64="Prepayment", "Update schedule, recalculate interest",J64="System Error", "Escalate to tech team",J64="Waiver Applied", "Verify approval, update ledger",J64="Partial Payment", "Contact customer for balance",J64="Rate Change", "Update loan agreement",J64="", "" ) | L64: =VLOOKUP(A64,LMS_Loan_Tape!A:Z,7,FALSE) -> Northern Arc | M64: =D64+H64 -> 114 | N64: =VLOOKUP(A64,LMS_Loan_Tape!A:Z,6,FALSE) -> Business Loan | O64: =VLOOKUP(A64, LMS_Loan_Tape!A63:Z1062,11,false) -> 7
A65: =IFERROR(__xludf.DUMMYFUNCTION("""COMPUTED_VALUE"""),"LN-10233") -> LN-10233 | B65: =IFERROR(__xludf.DUMMYFUNCTION("""COMPUTED_VALUE"""),59548.0) -> 59548 | C65: =IFERROR(__xludf.DUMMYFUNCTION("""COMPUTED_VALUE"""),59548.0) -> 59548 | D65: =IFERROR(__xludf.DUMMYFUNCTION("""COMPUTED_VALUE"""),0.0) -> 0 | E65: =IFERROR(__xludf.DUMMYFUNCTION("""COMPUTED_VALUE"""),0.0) -> 0 | F65: =IFERROR(__xludf.DUMMYFUNCTION("""COMPUTED_VALUE"""),22358.0) -> 22358 | G65: =IFERROR(__xludf.DUMMYFUNCTION("""COMPUTED_VALUE"""),22134.0) -> 22134 | H65: =IFERROR(__xludf.DUMMYFUNCTION("""COMPUTED_VALUE"""),224.0) -> 224 | I65: =IFERROR(__xludf.DUMMYFUNCTION("""COMPUTED_VALUE"""),"EXCEPTION") -> EXCEPTION | K65: =IFS(J65="Prepayment", "Update schedule, recalculate interest",J65="System Error", "Escalate to tech team",J65="Waiver Applied", "Verify approval, update ledger",J65="Partial Payment", "Contact customer for balance",J65="Rate Change", "Update loan agreement",J65="", "" ) | L65: =VLOOKUP(A65,LMS_Loan_Tape!A:Z,7,FALSE) -> Northern Arc | M65: =D65+H65 -> 224 | N65: =VLOOKUP(A65,LMS_Loan_Tape!A:Z,6,FALSE) -> Home Loan | O65: =VLOOKUP(A65, LMS_Loan_Tape!A64:Z1063,11,false) -> 1
A66: =IFERROR(__xludf.DUMMYFUNCTION("""COMPUTED_VALUE"""),"LN-10240") -> LN-10240 | B66: =IFERROR(__xludf.DUMMYFUNCTION("""COMPUTED_VALUE"""),32332.0) -> 32332 | C66: =IFERROR(__xludf.DUMMYFUNCTION("""COMPUTED_VALUE"""),31685.0) -> 31685 | D66: =IFERROR(__xludf.DUMMYFUNCTION("""COMPUTED_VALUE"""),647.0) -> 647 | E66: =IFERROR(__xludf.DUMMYFUNCTION("""COMPUTED_VALUE"""),0.02001113447977236) -> 0.020011134 | F66: =IFERROR(__xludf.DUMMYFUNCTION("""COMPUTED_VALUE"""),3140.0) -> 3140 | G66: =IFERROR(__xludf.DUMMYFUNCTION("""COMPUTED_VALUE"""),3140.0) -> 3140 | H66: =IFERROR(__xludf.DUMMYFUNCTION("""COMPUTED_VALUE"""),0.0) -> 0 | I66: =IFERROR(__xludf.DUMMYFUNCTION("""COMPUTED_VALUE"""),"EXCEPTION") -> EXCEPTION | K66: =IFS(J66="Prepayment", "Update schedule, recalculate interest",J66="System Error", "Escalate to tech team",J66="Waiver Applied", "Verify approval, update ledger",J66="Partial Payment", "Contact customer for balance",J66="Rate Change", "Update loan agreement",J66="", "" ) | L66: =VLOOKUP(A66,LMS_Loan_Tape!A:Z,7,FALSE) -> Tata Capital | M66: =D66+H66 -> 647 | N66: =VLOOKUP(A66,LMS_Loan_Tape!A:Z,6,FALSE) -> Business Loan | O66: =VLOOKUP(A66, LMS_Loan_Tape!A65:Z1064,11,false) -> 1
A67: =IFERROR(__xludf.DUMMYFUNCTION("""COMPUTED_VALUE"""),"LN-10241") -> LN-10241 | B67: =IFERROR(__xludf.DUMMYFUNCTION("""COMPUTED_VALUE"""),307415.0) -> 307415 | C67: =IFERROR(__xludf.DUMMYFUNCTION("""COMPUTED_VALUE"""),184449.0) -> 184449 | D67: =IFERROR(__xludf.DUMMYFUNCTION("""COMPUTED_VALUE"""),122966.0) -> 122966 | E67: =IFERROR(__xludf.DUMMYFUNCTION("""COMPUTED_VALUE"""),0.4) -> 0.4 | F67: =IFERROR(__xludf.DUMMYFUNCTION("""COMPUTED_VALUE"""),26739.0) -> 26739 | G67: =IFERROR(__xludf.DUMMYFUNCTION("""COMPUTED_VALUE"""),26739.0) -> 26739 | H67: =IFERROR(__xludf.DUMMYFUNCTION("""COMPUTED_VALUE"""),0.0) -> 0 | I67: =IFERROR(__xludf.DUMMYFUNCTION("""COMPUTED_VALUE"""),"EXCEPTION") -> EXCEPTION | J67: =IFERROR(__xludf.DUMMYFUNCTION("""COMPUTED_VALUE"""),"Partial Payment") -> Partial Payment | K67: =IFS(J67="Prepayment", "Update schedule, recalculate interest",J67="System Error", "Escalate to tech team",J67="Waiver Applied", "Verify approval, update ledger",J67="Partial Payment", "Contact customer for balance",J67="Rate Change", "Update loan agreement",J67="", "" ) -> Contact customer for balance | L67: =VLOOKUP(A67,LMS_Loan_Tape!A:Z,7,FALSE) -> Piramal | M67: =D67+H67 -> 122966 | N67: =VLOOKUP(A67,LMS_Loan_Tape!A:Z,6,FALSE) -> Home Loan | O67: =VLOOKUP(A67, LMS_Loan_Tape!A66:Z1065,11,false) -> 12
A68: =IFERROR(__xludf.DUMMYFUNCTION("""COMPUTED_VALUE"""),"LN-10242") -> LN-10242 | B68: =IFERROR(__xludf.DUMMYFUNCTION("""COMPUTED_VALUE"""),56302.0) -> 56302 | C68: =IFERROR(__xludf.DUMMYFUNCTION("""COMPUTED_VALUE"""),55175.0) -> 55175 | D68: =IFERROR(__xludf.DUMMYFUNCTION("""COMPUTED_VALUE"""),1127.0) -> 1127 | E68: =IFERROR(__xludf.DUMMYFUNCTION("""COMPUTED_VALUE"""),0.020017050904053143) -> 0.020017051 | F68: =IFERROR(__xludf.DUMMYFUNCTION("""COMPUTED_VALUE"""),5849.0) -> 5849 | G68: =IFERROR(__xludf.DUMMYFUNCTION("""COMPUTED_VALUE"""),5849.0) -> 5849 | H68: =IFERROR(__xludf.DUMMYFUNCTION("""COMPUTED_VALUE"""),0.0) -> 0 | I68: =IFERROR(__xludf.DUMMYFUNCTION("""COMPUTED_VALUE"""),"EXCEPTION") -> EXCEPTION | K68: =IFS(J68="Prepayment", "Update schedule, recalculate interest",J68="System Error", "Escalate to tech team",J68="Waiver Applied", "Verify approval, update ledger",J68="Partial Payment", "Contact customer for balance",J68="Rate Change", "Update loan agreement",J68="", "" ) | L68: =VLOOKUP(A68,LMS_Loan_Tape!A:Z,7,FALSE) -> Piramal | M68: =D68+H68 -> 1127 | N68: =VLOOKUP(A68,LMS_Loan_Tape!A:Z,6,FALSE) -> Home Loan | O68: =VLOOKUP(A68, LMS_Loan_Tape!A67:Z1066,11,false) -> 1
A69: =IFERROR(__xludf.DUMMYFUNCTION("""COMPUTED_VALUE"""),"LN-10245") -> LN-10245 | B69: =IFERROR(__xludf.DUMMYFUNCTION("""COMPUTED_VALUE"""),28873.0) -> 28873 | C69: =IFERROR(__xludf.DUMMYFUNCTION("""COMPUTED_VALUE"""),28295.0) -> 28295 | D69: =IFERROR(__xludf.DUMMYFUNCTION("""COMPUTED_VALUE"""),578.0) -> 578 | E69: =IFERROR(__xludf.DUMMYFUNCTION("""COMPUTED_VALUE"""),0.020018702594119073) -> 0.020018703 | F69: =IFERROR(__xludf.DUMMYFUNCTION("""COMPUTED_VALUE"""),4885.0) -> 4885 | G69: =IFERROR(__xludf.DUMMYFUNCTION("""COMPUTED_VALUE"""),4885.0) -> 4885 | H69: =IFERROR(__xludf.DUMMYFUNCTION("""COMPUTED_VALUE"""),0.0) -> 0 | I69: =IFERROR(__xludf.DUMMYFUNCTION("""COMPUTED_VALUE"""),"EXCEPTION") -> EXCEPTION | K69: =IFS(J69="Prepayment", "Update schedule, recalculate interest",J69="System Error", "Escalate to tech team",J69="Waiver Applied", "Verify approval, update ledger",J69="Partial Payment", "Contact customer for balance",J69="Rate Change", "Update loan agreement",J69="", "" ) | L69: =VLOOKUP(A69,LMS_Loan_Tape!A:Z,7,FALSE) -> Liquiloans | M69: =D69+H69 -> 578 | N69: =VLOOKUP(A69,LMS_Loan_Tape!A:Z,6,FALSE) -> Personal Loan | O69: =VLOOKUP(A69, LMS_Loan_Tape!A68:Z1067,11,false) -> 8
A70: =IFERROR(__xludf.DUMMYFUNCTION("""COMPUTED_VALUE"""),"LN-10249") -> LN-10249 | B70: =IFERROR(__xludf.DUMMYFUNCTION("""COMPUTED_VALUE"""),138528.0) -> 138528 | C70: =IFERROR(__xludf.DUMMYFUNCTION("""COMPUTED_VALUE"""),138973.0) -> 138973 | D70: =IFERROR(__xludf.DUMMYFUNCTION("""COMPUTED_VALUE"""),-445.0) -> -445 | E70: =IFERROR(__xludf.DUMMYFUNCTION("""COMPUTED_VALUE"""),-0.003212346962346962) -> -0.003212347 | F70: =IFERROR(__xludf.DUMMYFUNCTION("""COMPUTED_VALUE"""),29320.0) -> 29320 | G70: =IFERROR(__xludf.DUMMYFUNCTION("""COMPUTED_VALUE"""),29320.0) -> 29320 | H70: =IFERROR(__xludf.DUMMYFUNCTION("""COMPUTED_VALUE"""),0.0) -> 0 | I70: =IFERROR(__xludf.DUMMYFUNCTION("""COMPUTED_VALUE"""),"EXCEPTION") -> EXCEPTION | J70: =IFERROR(__xludf.DUMMYFUNCTION("""COMPUTED_VALUE"""),"System Error") -> System Error | K70: =IFS(J70="Prepayment", "Update schedule, recalculate interest",J70="System Error", "Escalate to tech team",J70="Waiver Applied", "Verify approval, update ledger",J70="Partial Payment", "Contact customer for balance",J70="Rate Change", "Update loan agreement",J70="", "" ) -> Escalate to tech team | L70: =VLOOKUP(A70,LMS_Loan_Tape!A:Z,7,FALSE) -> Tata Capital | M70: =D70+H70 -> -445 | N70: =VLOOKUP(A70,LMS_Loan_Tape!A:Z,6,FALSE) -> Home Loan | O70: =VLOOKUP(A70, LMS_Loan_Tape!A69:Z1068,11,false) -> 11
A71: =IFERROR(__xludf.DUMMYFUNCTION("""COMPUTED_VALUE"""),"LN-10250") -> LN-10250 | B71: =IFERROR(__xludf.DUMMYFUNCTION("""COMPUTED_VALUE"""),312120.0) -> 312120 | C71: =IFERROR(__xludf.DUMMYFUNCTION("""COMPUTED_VALUE"""),312120.0) -> 312120 | D71: =IFERROR(__xludf.DUMMYFUNCTION("""COMPUTED_VALUE"""),0.0) -> 0 | E71: =IFERROR(__xludf.DUMMYFUNCTION("""COMPUTED_VALUE"""),0.0) -> 0 | F71: =IFERROR(__xludf.DUMMYFUNCTION("""COMPUTED_VALUE"""),26366.0) -> 26366 | G71: =IFERROR(__xludf.DUMMYFUNCTION("""COMPUTED_VALUE"""),26102.0) -> 26102 | H71: =IFERROR(__xludf.DUMMYFUNCTION("""COMPUTED_VALUE"""),264.0) -> 264 | I71: =IFERROR(__xludf.DUMMYFUNCTION("""COMPUTED_VALUE"""),"EXCEPTION") -> EXCEPTION | K71: =IFS(J71="Prepayment", "Update schedule, recalculate interest",J71="System Error", "Escalate to tech team",J71="Waiver Applied", "Verify approval, update ledger",J71="Partial Payment", "Contact customer for balance",J71="Rate Change", "Update loan agreement",J71="", "" ) | L71: =VLOOKUP(A71,LMS_Loan_Tape!A:Z,7,FALSE) -> Piramal | M71: =D71+H71 -> 264 | N71: =VLOOKUP(A71,LMS_Loan_Tape!A:Z,6,FALSE) -> Home Loan | O71: =VLOOKUP(A71, LMS_Loan_Tape!A70:Z1069,11,false) -> 12
A72: =IFERROR(__xludf.DUMMYFUNCTION("""COMPUTED_VALUE"""),"LN-10252") -> LN-10252 | B72: =IFERROR(__xludf.DUMMYFUNCTION("""COMPUTED_VALUE"""),29041.0) -> 29041 | C72: =IFERROR(__xludf.DUMMYFUNCTION("""COMPUTED_VALUE"""),23232.0) -> 23232 | D72: =IFERROR(__xludf.DUMMYFUNCTION("""COMPUTED_VALUE"""),5809.0) -> 5809 | E72: =IFERROR(__xludf.DUMMYFUNCTION("""COMPUTED_VALUE"""),0.20002754726076927) -> 0.20002755 | F72: =IFERROR(__xludf.DUMMYFUNCTION("""COMPUTED_VALUE"""),6557.0) -> 6557 | G72: =IFERROR(__xludf.DUMMYFUNCTION("""COMPUTED_VALUE"""),6557.0) -> 6557 | H72: =IFERROR(__xludf.DUMMYFUNCTION("""COMPUTED_VALUE"""),0.0) -> 0 | I72: =IFERROR(__xludf.DUMMYFUNCTION("""COMPUTED_VALUE"""),"EXCEPTION") -> EXCEPTION | J72: =IFERROR(__xludf.DUMMYFUNCTION("""COMPUTED_VALUE"""),"Prepayment") -> Prepayment | K72: =IFS(J72="Prepayment", "Update schedule, recalculate interest",J72="System Error", "Escalate to tech team",J72="Waiver Applied", "Verify approval, update ledger",J72="Partial Payment", "Contact customer for balance",J72="Rate Change", "Update loan agreement",J72="", "" ) -> Update schedule, recalculate interest | L72: =VLOOKUP(A72,LMS_Loan_Tape!A:Z,7,FALSE) -> Liquiloans | M72: =D72+H72 -> 5809 | N72: =VLOOKUP(A72,LMS_Loan_Tape!A:Z,6,FALSE) -> Business Loan | O72: =VLOOKUP(A72, LMS_Loan_Tape!A71:Z1070,11,false) -> 10
A73: =IFERROR(__xludf.DUMMYFUNCTION("""COMPUTED_VALUE"""),"LN-10254") -> LN-10254 | B73: =IFERROR(__xludf.DUMMYFUNCTION("""COMPUTED_VALUE"""),149578.0) -> 149578 | C73: =IFERROR(__xludf.DUMMYFUNCTION("""COMPUTED_VALUE"""),149578.0) -> 149578 | D73: =IFERROR(__xludf.DUMMYFUNCTION("""COMPUTED_VALUE"""),0.0) -> 0 | E73: =IFERROR(__xludf.DUMMYFUNCTION("""COMPUTED_VALUE"""),0.0) -> 0 | F73: =IFERROR(__xludf.DUMMYFUNCTION("""COMPUTED_VALUE"""),16556.0) -> 16556 | G73: =IFERROR(__xludf.DUMMYFUNCTION("""COMPUTED_VALUE"""),16390.0) -> 16390 | H73: =IFERROR(__xludf.DUMMYFUNCTION("""COMPUTED_VALUE"""),166.0) -> 166 | I73: =IFERROR(__xludf.DUMMYFUNCTION("""COMPUTED_VALUE"""),"EXCEPTION") -> EXCEPTION | K73: =IFS(J73="Prepayment", "Update schedule, recalculate interest",J73="System Error", "Escalate to tech team",J73="Waiver Applied", "Verify approval, update ledger",J73="Partial Payment", "Contact customer for balance",J73="Rate Change", "Update loan agreement",J73="", "" ) | L73: =VLOOKUP(A73,LMS_Loan_Tape!A:Z,7,FALSE) -> Northern Arc | M73: =D73+H73 -> 166 | N73: =VLOOKUP(A73,LMS_Loan_Tape!A:Z,6,FALSE) -> Business Loan | O73: =VLOOKUP(A73, LMS_Loan_Tape!A72:Z1071,11,false) -> 2
A74: =IFERROR(__xludf.DUMMYFUNCTION("""COMPUTED_VALUE"""),"LN-10255") -> LN-10255 | B74: =IFERROR(__xludf.DUMMYFUNCTION("""COMPUTED_VALUE"""),133519.0) -> 133519 | C74: =IFERROR(__xludf.DUMMYFUNCTION("""COMPUTED_VALUE"""),133519.0) -> 133519 | D74: =IFERROR(__xludf.DUMMYFUNCTION("""COMPUTED_VALUE"""),0.0) -> 0 | E74: =IFERROR(__xludf.DUMMYFUNCTION("""COMPUTED_VALUE"""),0.0) -> 0 | F74: =IFERROR(__xludf.DUMMYFUNCTION("""COMPUTED_VALUE"""),9358.0) -> 9358 | G74: =IFERROR(__xludf.DUMMYFUNCTION("""COMPUTED_VALUE"""),9264.0) -> 9264 | H74: =IFERROR(__xludf.DUMMYFUNCTION("""COMPUTED_VALUE"""),94.0) -> 94 | I74: =IFERROR(__xludf.DUMMYFUNCTION("""COMPUTED_VALUE"""),"EXCEPTION") -> EXCEPTION | K74: =IFS(J74="Prepayment", "Update schedule, recalculate interest",J74="System Error", "Escalate to tech team",J74="Waiver Applied", "Verify approval, update ledger",J74="Partial Payment", "Contact customer for balance",J74="Rate Change", "Update loan agreement",J74="", "" ) | L74: =VLOOKUP(A74,LMS_Loan_Tape!A:Z,7,FALSE) -> Northern Arc | M74: =D74+H74 -> 94 | N74: =VLOOKUP(A74,LMS_Loan_Tape!A:Z,6,FALSE) -> Personal Loan | O74: =VLOOKUP(A74, LMS_Loan_Tape!A73:Z1072,11,false) -> 3
A75: =IFERROR(__xludf.DUMMYFUNCTION("""COMPUTED_VALUE"""),"LN-10257") -> LN-10257 | B75: =IFERROR(__xludf.DUMMYFUNCTION("""COMPUTED_VALUE"""),98446.0) -> 98446 | C75: =IFERROR(__xludf.DUMMYFUNCTION("""COMPUTED_VALUE"""),59067.0) -> 59067 | D75: =IFERROR(__xludf.DUMMYFUNCTION("""COMPUTED_VALUE"""),39379.0) -> 39379 | E75: =IFERROR(__xludf.DUMMYFUNCTION("""COMPUTED_VALUE"""),0.4000060947118217) -> 0.40000609 | F75: =IFERROR(__xludf.DUMMYFUNCTION("""COMPUTED_VALUE"""),9287.0) -> 9287 | G75: =IFERROR(__xludf.DUMMYFUNCTION("""COMPUTED_VALUE"""),9287.0) -> 9287 | H75: =IFERROR(__xludf.DUMMYFUNCTION("""COMPUTED_VALUE"""),0.0) -> 0 | I75: =IFERROR(__xludf.DUMMYFUNCTION("""COMPUTED_VALUE"""),"EXCEPTION") -> EXCEPTION | J75: =IFERROR(__xludf.DUMMYFUNCTION("""COMPUTED_VALUE"""),"Partial Payment") -> Partial Payment | K75: =IFS(J75="Prepayment", "Update schedule, recalculate interest",J75="System Error", "Escalate to tech team",J75="Waiver Applied", "Verify approval, update ledger",J75="Partial Payment", "Contact customer for balance",J75="Rate Change", "Update loan agreement",J75="", "" ) -> Contact customer for balance | L75: =VLOOKUP(A75,LMS_Loan_Tape!A:Z,7,FALSE) -> DMI | M75: =D75+H75 -> 39379 | N75: =VLOOKUP(A75,LMS_Loan_Tape!A:Z,6,FALSE) -> Personal Loan | O75: =VLOOKUP(A75, LMS_Loan_Tape!A74:Z1073,11,false) -> 8
A76: =IFERROR(__xludf.DUMMYFUNCTION("""COMPUTED_VALUE"""),"LN-10258") -> LN-10258 | B76: =IFERROR(__xludf.DUMMYFUNCTION("""COMPUTED_VALUE"""),107565.0) -> 107565 | C76: =IFERROR(__xludf.DUMMYFUNCTION("""COMPUTED_VALUE"""),64539.0) -> 64539 | D76: =IFERROR(__xludf.DUMMYFUNCTION("""COMPUTED_VALUE"""),43026.0) -> 43026 | E76: =IFERROR(__xludf.DUMMYFUNCTION("""COMPUTED_VALUE"""),0.4) -> 0.4 | F76: =IFERROR(__xludf.DUMMYFUNCTION("""COMPUTED_VALUE"""),24527.0) -> 24527 | G76: =IFERROR(__xludf.DUMMYFUNCTION("""COMPUTED_VALUE"""),24527.0) -> 24527 | H76: =IFERROR(__xludf.DUMMYFUNCTION("""COMPUTED_VALUE"""),0.0) -> 0 | I76: =IFERROR(__xludf.DUMMYFUNCTION("""COMPUTED_VALUE"""),"EXCEPTION") -> EXCEPTION | J76: =IFERROR(__xludf.DUMMYFUNCTION("""COMPUTED_VALUE"""),"Partial Payment") -> Partial Payment | K76: =IFS(J76="Prepayment", "Update schedule, recalculate interest",J76="System Error", "Escalate to tech team",J76="Waiver Applied", "Verify approval, update ledger",J76="Partial Payment", "Contact customer for balance",J76="Rate Change", "Update loan agreement",J76="", "" ) -> Contact customer for balance | L76: =VLOOKUP(A76,LMS_Loan_Tape!A:Z,7,FALSE) -> DMI | M76: =D76+H76 -> 43026 | N76: =VLOOKUP(A76,LMS_Loan_Tape!A:Z,6,FALSE) -> Personal Loan | O76: =VLOOKUP(A76, LMS_Loan_Tape!A75:Z1074,11,false) -> 11
A77: =IFERROR(__xludf.DUMMYFUNCTION("""COMPUTED_VALUE"""),"LN-10260") -> LN-10260 | B77: =IFERROR(__xludf.DUMMYFUNCTION("""COMPUTED_VALUE"""),277903.0) -> 277903 | C77: =IFERROR(__xludf.DUMMYFUNCTION("""COMPUTED_VALUE"""),166741.0) -> 166741 | D77: =IFERROR(__xludf.DUMMYFUNCTION("""COMPUTED_VALUE"""),111162.0) -> 111162 | E77: =IFERROR(__xludf.DUMMYFUNCTION("""COMPUTED_VALUE"""),0.400002878702281) -> 0.40000288 | F77: =IFERROR(__xludf.DUMMYFUNCTION("""COMPUTED_VALUE"""),39573.0) -> 39573 | G77: =IFERROR(__xludf.DUMMYFUNCTION("""COMPUTED_VALUE"""),39573.0) -> 39573 | H77: =IFERROR(__xludf.DUMMYFUNCTION("""COMPUTED_VALUE"""),0.0) -> 0 | I77: =IFERROR(__xludf.DUMMYFUNCTION("""COMPUTED_VALUE"""),"EXCEPTION") -> EXCEPTION | J77: =IFERROR(__xludf.DUMMYFUNCTION("""COMPUTED_VALUE"""),"Partial Payment") -> Partial Payment | K77: =IFS(J77="Prepayment", "Update schedule, recalculate interest",J77="System Error", "Escalate to tech team",J77="Waiver Applied", "Verify approval, update ledger",J77="Partial Payment", "Contact customer for balance",J77="Rate Change", "Update loan agreement",J77="", "" ) -> Contact customer for balance | L77: =VLOOKUP(A77,LMS_Loan_Tape!A:Z,7,FALSE) -> Tata Capital | M77: =D77+H77 -> 111162 | N77: =VLOOKUP(A77,LMS_Loan_Tape!A:Z,6,FALSE) -> Business Loan | O77: =VLOOKUP(A77, LMS_Loan_Tape!A76:Z1075,11,false) -> 1
A78: =IFERROR(__xludf.DUMMYFUNCTION("""COMPUTED_VALUE"""),"LN-10264") -> LN-10264 | B78: =IFERROR(__xludf.DUMMYFUNCTION("""COMPUTED_VALUE"""),59348.0) -> 59348 | C78: =IFERROR(__xludf.DUMMYFUNCTION("""COMPUTED_VALUE"""),53413.0) -> 53413 | D78: =IFERROR(__xludf.DUMMYFUNCTION("""COMPUTED_VALUE"""),5935.0) -> 5935 | E78: =IFERROR(__xludf.DUMMYFUNCTION("""COMPUTED_VALUE"""),0.10000336995349464) -> 0.10000337 | F78: =IFERROR(__xludf.DUMMYFUNCTION("""COMPUTED_VALUE"""),23143.0) -> 23143 | G78: =IFERROR(__xludf.DUMMYFUNCTION("""COMPUTED_VALUE"""),11571.0) -> 11571 | H78: =IFERROR(__xludf.DUMMYFUNCTION("""COMPUTED_VALUE"""),11572.0) -> 11572 | I78: =IFERROR(__xludf.DUMMYFUNCTION("""COMPUTED_VALUE"""),"EXCEPTION") -> EXCEPTION | J78: =IFERROR(__xludf.DUMMYFUNCTION("""COMPUTED_VALUE"""),"Waiver Applied") -> Waiver Applied | K78: =IFS(J78="Prepayment", "Update schedule, recalculate interest",J78="System Error", "Escalate to tech team",J78="Waiver Applied", "Verify approval, update ledger",J78="Partial Payment", "Contact customer for balance",J78="Rate Change", "Update loan agreement",J78="", "" ) -> Verify approval, update ledger | L78: =VLOOKUP(A78,LMS_Loan_Tape!A:Z,7,FALSE) -> Liquiloans | M78: =D78+H78 -> 17507 | N78: =VLOOKUP(A78,LMS_Loan_Tape!A:Z,6,FALSE) -> Personal Loan | O78: =VLOOKUP(A78, LMS_Loan_Tape!A77:Z1076,11,false) -> 11
A79: =IFERROR(__xludf.DUMMYFUNCTION("""COMPUTED_VALUE"""),"LN-10265") -> LN-10265 | B79: =IFERROR(__xludf.DUMMYFUNCTION("""COMPUTED_VALUE"""),262408.0) -> 262408 | C79: =IFERROR(__xludf.DUMMYFUNCTION("""COMPUTED_VALUE"""),257159.0) -> 257159 | D79: =IFERROR(__xludf.DUMMYFUNCTION("""COMPUTED_VALUE"""),5249.0) -> 5249 | E79: =IFERROR(__xludf.DUMMYFUNCTION("""COMPUTED_VALUE"""),0.020003201121917016) -> 0.020003201 | F79: =IFERROR(__xludf.DUMMYFUNCTION("""COMPUTED_VALUE"""),48464.0) -> 48464 | G79: =IFERROR(__xludf.DUMMYFUNCTION("""COMPUTED_VALUE"""),48464.0) -> 48464 | H79: =IFERROR(__xludf.DUMMYFUNCTION("""COMPUTED_VALUE"""),0.0) -> 0 | I79: =IFERROR(__xludf.DUMMYFUNCTION("""COMPUTED_VALUE"""),"EXCEPTION") -> EXCEPTION | K79: =IFS(J79="Prepayment", "Update schedule, recalculate interest",J79="System Error", "Escalate to tech team",J79="Waiver Applied", "Verify approval, update ledger",J79="Partial Payment", "Contact customer for balance",J79="Rate Change", "Update loan agreement",J79="", "" ) | L79: =VLOOKUP(A79,LMS_Loan_Tape!A:Z,7,FALSE) -> DMI | M79: =D79+H79 -> 5249 | N79: =VLOOKUP(A79,LMS_Loan_Tape!A:Z,6,FALSE) -> Business Loan | O79: =VLOOKUP(A79, LMS_Loan_Tape!A78:Z1077,11,false) -> 9
A80: =IFERROR(__xludf.DUMMYFUNCTION("""COMPUTED_VALUE"""),"LN-10272") -> LN-10272 | B80: =IFERROR(__xludf.DUMMYFUNCTION("""COMPUTED_VALUE"""),149144.0) -> 149144 | C80: =IFERROR(__xludf.DUMMYFUNCTION("""COMPUTED_VALUE"""),89486.0) -> 89486 | D80: =IFERROR(__xludf.DUMMYFUNCTION("""COMPUTED_VALUE"""),59658.0) -> 59658 | E80: =IFERROR(__xludf.DUMMYFUNCTION("""COMPUTED_VALUE"""),0.4000026819717857) -> 0.40000268 | F80: =IFERROR(__xludf.DUMMYFUNCTION("""COMPUTED_VALUE"""),22740.0) -> 22740 | G80: =IFERROR(__xludf.DUMMYFUNCTION("""COMPUTED_VALUE"""),22740.0) -> 22740 | H80: =IFERROR(__xludf.DUMMYFUNCTION("""COMPUTED_VALUE"""),0.0) -> 0 | I80: =IFERROR(__xludf.DUMMYFUNCTION("""COMPUTED_VALUE"""),"EXCEPTION") -> EXCEPTION | J80: =IFERROR(__xludf.DUMMYFUNCTION("""COMPUTED_VALUE"""),"Partial Payment") -> Partial Payment | K80: =IFS(J80="Prepayment", "Update schedule, recalculate interest",J80="System Error", "Escalate to tech team",J80="Waiver Applied", "Verify approval, update ledger",J80="Partial Payment", "Contact customer for balance",J80="Rate Change", "Update loan agreement",J80="", "" ) -> Contact customer for balance | L80: =VLOOKUP(A80,LMS_Loan_Tape!A:Z,7,FALSE) -> Piramal | M80: =D80+H80 -> 59658 | N80: =VLOOKUP(A80,LMS_Loan_Tape!A:Z,6,FALSE) -> Gold Loan | O80: =VLOOKUP(A80, LMS_Loan_Tape!A79:Z1078,11,false) -> 9
A81: =IFERROR(__xludf.DUMMYFUNCTION("""COMPUTED_VALUE"""),"LN-10274") -> LN-10274 | B81: =IFERROR(__xludf.DUMMYFUNCTION("""COMPUTED_VALUE"""),47347.0) -> 47347 | C81: =IFERROR(__xludf.DUMMYFUNCTION("""COMPUTED_VALUE"""),42612.0) -> 42612 | D81: =IFERROR(__xludf.DUMMYFUNCTION("""COMPUTED_VALUE"""),4735.0) -> 4735 | E81: =IFERROR(__xludf.DUMMYFUNCTION("""COMPUTED_VALUE"""),0.1000063361987032) -> 0.10000634 | F81: =IFERROR(__xludf.DUMMYFUNCTION("""COMPUTED_VALUE"""),5946.0) -> 5946 | G81: =IFERROR(__xludf.DUMMYFUNCTION("""COMPUTED_VALUE"""),2973.0) -> 2973 | H81: =IFERROR(__xludf.DUMMYFUNCTION("""COMPUTED_VALUE"""),2973.0) -> 2973 | I81: =IFERROR(__xludf.DUMMYFUNCTION("""COMPUTED_VALUE"""),"EXCEPTION") -> EXCEPTION | J81: =IFERROR(__xludf.DUMMYFUNCTION("""COMPUTED_VALUE"""),"Waiver Applied") -> Waiver Applied | K81: =IFS(J81="Prepayment", "Update schedule, recalculate interest",J81="System Error", "Escalate to tech team",J81="Waiver Applied", "Verify approval, update ledger",J81="Partial Payment", "Contact customer for balance",J81="Rate Change", "Update loan agreement",J81="", "" ) -> Verify approval, update ledger | L81: =VLOOKUP(A81,LMS_Loan_Tape!A:Z,7,FALSE) -> DMI | M81: =D81+H81 -> 7708 | N81: =VLOOKUP(A81,LMS_Loan_Tape!A:Z,6,FALSE) -> Home Loan | O81: =VLOOKUP(A81, LMS_Loan_Tape!A80:Z1079,11,false) -> 2
A82: =IFERROR(__xludf.DUMMYFUNCTION("""COMPUTED_VALUE"""),"LN-10281") -> LN-10281 | B82: =IFERROR(__xludf.DUMMYFUNCTION("""COMPUTED_VALUE"""),35631.0) -> 35631 | C82: =IFERROR(__xludf.DUMMYFUNCTION("""COMPUTED_VALUE"""),35631.0) -> 35631 | D82: =IFERROR(__xludf.DUMMYFUNCTION("""COMPUTED_VALUE"""),0.0) -> 0 | E82: =IFERROR(__xludf.DUMMYFUNCTION("""COMPUTED_VALUE"""),0.0) -> 0 | F82: =IFERROR(__xludf.DUMMYFUNCTION("""COMPUTED_VALUE"""),12070.0) -> 12070 | G82: =IFERROR(__xludf.DUMMYFUNCTION("""COMPUTED_VALUE"""),11949.0) -> 11949 | H82: =IFERROR(__xludf.DUMMYFUNCTION("""COMPUTED_VALUE"""),121.0) -> 121 | I82: =IFERROR(__xludf.DUMMYFUNCTION("""COMPUTED_VALUE"""),"EXCEPTION") -> EXCEPTION | K82: =IFS(J82="Prepayment", "Update schedule, recalculate interest",J82="System Error", "Escalate to tech team",J82="Waiver Applied", "Verify approval, update ledger",J82="Partial Payment", "Contact customer for balance",J82="Rate Change", "Update loan agreement",J82="", "" ) | L82: =VLOOKUP(A82,LMS_Loan_Tape!A:Z,7,FALSE) -> Northern Arc | M82: =D82+H82 -> 121 | N82: =VLOOKUP(A82,LMS_Loan_Tape!A:Z,6,FALSE) -> Business Loan | O82: =VLOOKUP(A82, LMS_Loan_Tape!A81:Z1080,11,false) -> 10
A83: =IFERROR(__xludf.DUMMYFUNCTION("""COMPUTED_VALUE"""),"LN-10285") -> LN-10285 | B83: =IFERROR(__xludf.DUMMYFUNCTION("""COMPUTED_VALUE"""),95404.0) -> 95404 | C83: =IFERROR(__xludf.DUMMYFUNCTION("""COMPUTED_VALUE"""),95404.0) -> 95404 | D83: =IFERROR(__xludf.DUMMYFUNCTION("""COMPUTED_VALUE"""),0.0) -> 0 | E83: =IFERROR(__xludf.DUMMYFUNCTION("""COMPUTED_VALUE"""),0.0) -> 0 | F83: =IFERROR(__xludf.DUMMYFUNCTION("""COMPUTED_VALUE"""),27458.0) -> 27458 | G83: =IFERROR(__xludf.DUMMYFUNCTION("""COMPUTED_VALUE"""),27183.0) -> 27183 | H83: =IFERROR(__xludf.DUMMYFUNCTION("""COMPUTED_VALUE"""),275.0) -> 275 | I83: =IFERROR(__xludf.DUMMYFUNCTION("""COMPUTED_VALUE"""),"EXCEPTION") -> EXCEPTION | K83: =IFS(J83="Prepayment", "Update schedule, recalculate interest",J83="System Error", "Escalate to tech team",J83="Waiver Applied", "Verify approval, update ledger",J83="Partial Payment", "Contact customer for balance",J83="Rate Change", "Update loan agreement",J83="", "" ) | L83: =VLOOKUP(A83,LMS_Loan_Tape!A:Z,7,FALSE) -> Tata Capital | M83: =D83+H83 -> 275 | N83: =VLOOKUP(A83,LMS_Loan_Tape!A:Z,6,FALSE) -> Gold Loan | O83: =VLOOKUP(A83, LMS_Loan_Tape!A82:Z1081,11,false) -> 11
A84: =IFERROR(__xludf.DUMMYFUNCTION("""COMPUTED_VALUE"""),"LN-10289") -> LN-10289 | B84: =IFERROR(__xludf.DUMMYFUNCTION("""COMPUTED_VALUE"""),223176.0) -> 223176 | C84: =IFERROR(__xludf.DUMMYFUNCTION("""COMPUTED_VALUE"""),223176.0) -> 223176 | D84: =IFERROR(__xludf.DUMMYFUNCTION("""COMPUTED_VALUE"""),0.0) -> 0 | E84: =IFERROR(__xludf.DUMMYFUNCTION("""COMPUTED_VALUE"""),0.0) -> 0 | F84: =IFERROR(__xludf.DUMMYFUNCTION("""COMPUTED_VALUE"""),39617.0) -> 39617 | G84: =IFERROR(__xludf.DUMMYFUNCTION("""COMPUTED_VALUE"""),39220.0) -> 39220 | H84: =IFERROR(__xludf.DUMMYFUNCTION("""COMPUTED_VALUE"""),397.0) -> 397 | I84: =IFERROR(__xludf.DUMMYFUNCTION("""COMPUTED_VALUE"""),"EXCEPTION") -> EXCEPTION | K84: =IFS(J84="Prepayment", "Update schedule, recalculate interest",J84="System Error", "Escalate to tech team",J84="Waiver Applied", "Verify approval, update ledger",J84="Partial Payment", "Contact customer for balance",J84="Rate Change", "Update loan agreement",J84="", "" ) | L84: =VLOOKUP(A84,LMS_Loan_Tape!A:Z,7,FALSE) -> Liquiloans | M84: =D84+H84 -> 397 | N84: =VLOOKUP(A84,LMS_Loan_Tape!A:Z,6,FALSE) -> Home Loan | O84: =VLOOKUP(A84, LMS_Loan_Tape!A83:Z1082,11,false) -> 8
A85: =IFERROR(__xludf.DUMMYFUNCTION("""COMPUTED_VALUE"""),"LN-10291") -> LN-10291 | B85: =IFERROR(__xludf.DUMMYFUNCTION("""COMPUTED_VALUE"""),141525.0) -> 141525 | C85: =IFERROR(__xludf.DUMMYFUNCTION("""COMPUTED_VALUE"""),148601.0) -> 148601 | D85: =IFERROR(__xludf.DUMMYFUNCTION("""COMPUTED_VALUE"""),-7076.0) -> -7076 | E85: =IFERROR(__xludf.DUMMYFUNCTION("""COMPUTED_VALUE"""),-0.04999823352764529) -> -0.049998234 | F85: =IFERROR(__xludf.DUMMYFUNCTION("""COMPUTED_VALUE"""),12129.0) -> 12129 | G85: =IFERROR(__xludf.DUMMYFUNCTION("""COMPUTED_VALUE"""),12129.0) -> 12129 | H85: =IFERROR(__xludf.DUMMYFUNCTION("""COMPUTED_VALUE"""),0.0) -> 0 | I85: =IFERROR(__xludf.DUMMYFUNCTION("""COMPUTED_VALUE"""),"EXCEPTION") -> EXCEPTION | J85: =IFERROR(__xludf.DUMMYFUNCTION("""COMPUTED_VALUE"""),"Rate Change") -> Rate Change | K85: =IFS(J85="Prepayment", "Update schedule, recalculate interest",J85="System Error", "Escalate to tech team",J85="Waiver Applied", "Verify approval, update ledger",J85="Partial Payment", "Contact customer for balance",J85="Rate Change", "Update loan agreement",J85="", "" ) -> Update loan agreement | L85: =VLOOKUP(A85,LMS_Loan_Tape!A:Z,7,FALSE) -> Liquiloans | M85: =D85+H85 -> -7076 | N85: =VLOOKUP(A85,LMS_Loan_Tape!A:Z,6,FALSE) -> Gold Loan | O85: =VLOOKUP(A85, LMS_Loan_Tape!A84:Z1083,11,false) -> 7
A86: =IFERROR(__xludf.DUMMYFUNCTION("""COMPUTED_VALUE"""),"LN-10293") -> LN-10293 | B86: =IFERROR(__xludf.DUMMYFUNCTION("""COMPUTED_VALUE"""),73572.0) -> 73572 | C86: =IFERROR(__xludf.DUMMYFUNCTION("""COMPUTED_VALUE"""),66214.0) -> 66214 | D86: =IFERROR(__xludf.DUMMYFUNCTION("""COMPUTED_VALUE"""),7358.0) -> 7358 | E86: =IFERROR(__xludf.DUMMYFUNCTION("""COMPUTED_VALUE"""),0.10001087370195183) -> 0.10001087 | F86: =IFERROR(__xludf.DUMMYFUNCTION("""COMPUTED_VALUE"""),10115.0) -> 10115 | G86: =IFERROR(__xludf.DUMMYFUNCTION("""COMPUTED_VALUE"""),5057.0) -> 5057 | H86: =IFERROR(__xludf.DUMMYFUNCTION("""COMPUTED_VALUE"""),5058.0) -> 5058 | I86: =IFERROR(__xludf.DUMMYFUNCTION("""COMPUTED_VALUE"""),"EXCEPTION") -> EXCEPTION | J86: =IFERROR(__xludf.DUMMYFUNCTION("""COMPUTED_VALUE"""),"Waiver Applied") -> Waiver Applied | K86: =IFS(J86="Prepayment", "Update schedule, recalculate interest",J86="System Error", "Escalate to tech team",J86="Waiver Applied", "Verify approval, update ledger",J86="Partial Payment", "Contact customer for balance",J86="Rate Change", "Update loan agreement",J86="", "" ) -> Verify approval, update ledger | L86: =VLOOKUP(A86,LMS_Loan_Tape!A:Z,7,FALSE) -> Northern Arc | M86: =D86+H86 -> 12416 | N86: =VLOOKUP(A86,LMS_Loan_Tape!A:Z,6,FALSE) -> Personal Loan | O86: =VLOOKUP(A86, LMS_Loan_Tape!A85:Z1084,11,false) -> 11
A87: =IFERROR(__xludf.DUMMYFUNCTION("""COMPUTED_VALUE"""),"LN-10294") -> LN-10294 | B87: =IFERROR(__xludf.DUMMYFUNCTION("""COMPUTED_VALUE"""),81747.0) -> 81747 | C87: =IFERROR(__xludf.DUMMYFUNCTION("""COMPUTED_VALUE"""),80112.0) -> 80112 | D87: =IFERROR(__xludf.DUMMYFUNCTION("""COMPUTED_VALUE"""),1635.0) -> 1635 | E87: =IFERROR(__xludf.DUMMYFUNCTION("""COMPUTED_VALUE"""),0.020000733971888878) -> 0.020000734 | F87: =IFERROR(__xludf.DUMMYFUNCTION("""COMPUTED_VALUE"""),6922.0) -> 6922 | G87: =IFERROR(__xludf.DUMMYFUNCTION("""COMPUTED_VALUE"""),6922.0) -> 6922 | H87: =IFERROR(__xludf.DUMMYFUNCTION("""COMPUTED_VALUE"""),0.0) -> 0 | I87: =IFERROR(__xludf.DUMMYFUNCTION("""COMPUTED_VALUE"""),"EXCEPTION") -> EXCEPTION | K87: =IFS(J87="Prepayment", "Update schedule, recalculate interest",J87="System Error", "Escalate to tech team",J87="Waiver Applied", "Verify approval, update ledger",J87="Partial Payment", "Contact customer for balance",J87="Rate Change", "Update loan agreement",J87="", "" ) | L87: =VLOOKUP(A87,LMS_Loan_Tape!A:Z,7,FALSE) -> Tata Capital | M87: =D87+H87 -> 1635 | N87: =VLOOKUP(A87,LMS_Loan_Tape!A:Z,6,FALSE) -> Home Loan | O87: =VLOOKUP(A87, LMS_Loan_Tape!A86:Z1085,11,false) -> 4

Sheet Dashboard
A12: product_type | B12: COUNTA of loan_id | C12: SUM of Total variance
B13: 0 | C13: 0
A14: Business Loan | B14: 20 | C14: 288475
A15: Gold Loan | B15: 16 | C15: 163941
A16: Home Loan | B16: 32 | C16: 434092
A17: Personal Loan | B17: 18 | C17: 168908
A18: Grand Total | B18: 86 | C18: 1055416
